Workbook
Name JR_PAGE_ANCHOR_0_1: CT!$A$1

Sheet BaoCao202510
A1: ID | B1: Tháng | C1: Tên HV | D1: Mã HV | E1: Lớp TT | F1: Môn Toán | G1: Môn Văn | H1: Môn Anh | I1: Môn Lý | J1: Môn Hóa | K1: Đơn giá | L1: Tổng số lượt | M1: Tổng số tiền | N1: Số thu được | O1: Ct | P1: TH | Q1: TM | R1: Phí TM | S1: Đóng dư tiền | T1: Số TK | U1: Tên TK | V1: Tên NH | W1: Địa chỉ | Y1: Hóa đơn 29
A2: 1 | B2: 202510 | C2: Trần Bảo Duy(NVC) | D2: SV10Ax1 | E2: 10A | F2: 3 | G2: 0 | H2: 0 | I2: 3 | J2: 0 | K2: 100000 | L2: =SUM(F2:J2) -> 6 | M2: =L2*K2 -> 600000 | N2: =M2 -> 600000 | P2: FT25298961227128 | S2: =M2-N2 -> 0 | T2: 0670190997777 | U2: NGUYEN THI HUYEN | V2: Ngân hàng MB
A3: 2 | B3: 202510 | C3: Nguyễn Thu Quyên | D3: SV10x10x1 | E3: 10A10 | F3: 5 | G3: 0 | H3: 3 | I3: 0 | J3: 0 | K3: 100000 | L3: =SUM(F3:J3) -> 8 | M3: =L3*K3 -> 800000 | N3: =M3 -> 800000 | P3: FT25308083720010 | S3: =M3-N3 -> 0 | T3: 0670190997777 | U3: NGUYEN THI HUYEN | V3: Ngân hàng MB
A4: 3 | B4: 202510 | C4: Hoàng Thanh Phong | D4: SV10x10x10 | E4: 10A10 | F4: 0 | G4: 0 | H4: 3 | I4: 0 | J4: 0 | K4: 100000 | L4: =SUM(F4:J4) -> 3 | M4: =L4*K4 -> 300000 | N4: =M4 -> 300000 | P4: FT25304886272980 | S4: =M4-N4 -> 0 | T4: 0670190997777 | U4: NGUYEN THI HUYEN | V4: Ngân hàng MB
A5: 4 | B5: 202510 | C5: Trần Quỳnh Anh | D5: SV10x10x11 | E5: 10A10 | F5: 6 | G5: 0 | H5: 4 | I5: 0 | J5: 0 | K5: 100000 | L5: =SUM(F5:J5) -> 10 | M5: =L5*K5 -> 1000000 | N5: =M5 -> 1000000 | P5: FT25302377371602 | S5: =M5-N5 -> 0 | T5: 0670190997777 | U5: NGUYEN THI HUYEN | V5: Ngân hàng MB
A6: 5 | B6: 202510 | C6: Đoàn Minh Ánh | D6: SV10x10x12 | E6: 10A10 | F6: 6 | G6: 0 | H6: 4 | I6: 4 | J6: 0 | K6: 100000 | L6: =SUM(F6:J6) -> 14 | M6: =L6*K6 -> 1400000 | N6: =M6 -> 1400000 | P6: FT25296991204506 | S6: =M6-N6 -> 0 | T6: 0670190997777 | U6: NGUYEN THI HUYEN | V6: Ngân hàng MB
A7: 6 | B7: 202510 | C7: Lê Vũ Bảo Anh | D7: SV10x10x13 | E7: 10A10 | F7: 6 | G7: 0 | H7: 0 | I7: 0 | J7: 0 | K7: 100000 | L7: =SUM(F7:J7) -> 6 | M7: =L7*K7 -> 600000 | N7: =M7 -> 600000 | P7: FT25305649357438 | S7: =M7-N7 -> 0 | T7: 0670190997777 | U7: NGUYEN THI HUYEN | V7: Ngân hàng MB
A8: 7 | B8: 202510 | C8: Bùi Đức Hải Minh | D8: SV10x10x14 | E8: 10A10 | F8: 6 | G8: 0 | H8: 0 | I8: 0 | J8: 0 | K8: 100000 | L8: =SUM(F8:J8) -> 6 | M8: =L8*K8 -> 600000 | N8: =M8 -> 600000 | P8: FT25304410010058 | S8: =M8-N8 -> 0 | T8: 0670190997777 | U8: NGUYEN THI HUYEN | V8: Ngân hàng MB
A9: 8 | B9: 202510 | C9: Đặng Anh Thư | D9: SV10x10x15 | E9: 10A10 | F9: 6 | G9: 0 | H9: 0 | I9: 0 | J9: 0 | K9: 100000 | L9: =SUM(F9:J9) -> 6 | M9: =L9*K9 -> 600000 | N9: =M9 -> 600000 | P9: FT25304301883414 | S9: =M9-N9 -> 0 | T9: 0670190997777 | U9: NGUYEN THI HUYEN | V9: Ngân hàng MB
A10: 9 | B10: 202510 | C10: Đỗ Anh Thư | D10: SV10x10x16 | E10: 10A10 | F10: 6 | G10: 0 | H10: 0 | I10: 0 | J10: 0 | K10: 100000 | L10: =SUM(F10:J10) -> 6 | M10: =L10*K10 -> 600000 | N10: =M10 -> 600000 | P10: FT25301102720132 | S10: =M10-N10 -> 0 | T10: 0670190997777 | U10: NGUYEN THI HUYEN | V10: Ngân hàng MB
A11: 10 | B11: 202510 | C11: Đỗ Đăng Dũng | D11: SV10x10x17 | E11: 10A10 | F11: 4 | G11: 0 | H11: 0 | I11: 0 | J11: 0 | K11: 100000 | L11: =SUM(F11:J11) -> 4 | M11: =L11*K11 -> 400000 | N11: =M11 -> 400000 | P11: FT25308446820372 | S11: =M11-N11 -> 0 | T11: 0670190997777 | U11: NGUYEN THI HUYEN | V11: Ngân hàng MB
A12: 11 | B12: 202510 | C12: Đỗ Quang Minh | D12: SV10x10x2 | E12: 10A10 | F12: 6 | G12: 0 | H12: 4 | I12: 0 | J12: 0 | K12: 100000 | L12: =SUM(F12:J12) -> 10 | M12: =L12*K12 -> 1000000 | N12: =M12 -> 1000000 | P12: FT25296196925791 | S12: =M12-N12 -> 0 | T12: 0670190997777 | U12: NGUYEN THI HUYEN | V12: Ngân hàng MB
A13: 12 | B13: 202510 | C13: Đoàn Tuệ Anh | D13: SV10x10x3 | E13: 10A10 | F13: 0 | G13: 0 | H13: 3 | I13: 3 | J13: 0 | K13: 100000 | L13: =SUM(F13:J13) -> 6 | M13: =L13*K13 -> 600000 | N13: =M13 -> 600000 | P13: FT25296986073542 FT25296415045814 | S13: =M13-N13 -> 0 | T13: 0670190997777 | U13: NGUYEN THI HUYEN | V13: Ngân hàng MB
... A17: 16 | B17: 202510 | C17: Nguyễn Thanh Bình | D17: SV10x10x7 | E17: 10A10 | F17: 0 | G17: 0 | H17: 4 | I17: 4 | J17: 0 | K17: 100000 | L17: =SUM(F17:J17) -> 8 | M17: =L17*K17 -> 800000 | N17: =M17 -> 800000 | P17: FT25295710705788 | S17: =M17-N17 -> 0 | T17: 0670190997777 | U17: NGUYEN THI HUYEN | V17: Ngân hàng MB
A18: 17 | B18: 202510 | C18: Đào Xuân Bách | D18: SV10x10x8 | E18: 10A10 | F18: 0 | G18: 0 | H18: 2 | I18: 0 | J18: 0 | K18: 100000 | L18: =SUM(F18:J18) -> 2 | M18: =L18*K18 -> 200000 | N18: 200000 | P18: FT25295687224836 | S18: =M18-N18 -> 0 | T18: 0670190997777 | U18: NGUYEN THI HUYEN | V18: Ngân hàng MB
A19: 18 | B19: 202510 | C19: Nguyễn Đức Bảo | D19: SV10x10x9 | E19: 10A10 | F19: 0 | G19: 0 | H19: 4 | I19: 0 | J19: 0 | K19: 100000 | L19: =SUM(F19:J19) -> 4 | M19: =L19*K19 -> 400000 | N19: =M19 -> 400000 | P19: FT25298922961220 | S19: =M19-N19 -> 0 | T19: 0670190997777 | U19: NGUYEN THI HUYEN | V19: Ngân hàng MB
A20: 19 | B20: 202510 | C20: Đào Thu An | D20: SV10x12x1 | E20: 10A12 | F20: 6 | G20: 4 | H20: 5 | I20: 4 | J20: 0 | K20: 100000 | L20: =SUM(F20:J20) -> 19 | M20: =L20*K20 -> 1900000 | N20: =M20 -> 1900000 | P20: FT25300924002780 | S20: =M20-N20 -> 0 | T20: 0670190997777 | U20: NGUYEN THI HUYEN | V20: Ngân hàng MB
A21: 20 | B21: 202510 | C21: Ngô Phạm An Phương | D21: SV10x12x10 | E21: 10A12 | F21: 0 | G21: 4 | H21: 5 | I21: 0 | J21: 0 | K21: 100000 | L21: =SUM(F21:J21) -> 9 | M21: =L21*K21 -> 900000 | N21: =M21 -> 900000 | P21: FT25305848300230 | S21: =M21-N21 -> 0 | T21: 0670190997777 | U21: NGUYEN THI HUYEN | V21: Ngân hàng MB
A22: 21 | B22: 202510 | C22: Đoàn Minh Quân | D22: SV10x12x11 | E22: 10A12 | F22: 6 | G22: 4 | H22: 5 | I22: 4 | J22: 0 | K22: 100000 | L22: =SUM(F22:J22) -> 19 | M22: =L22*K22 -> 1900000 | N22: =M20 -> 1900000 | P22: FT25298392452070 | S22: =M22-N22 -> 0 | T22: 0670190997777 | U22: NGUYEN THI HUYEN | V22: Ngân hàng MB
A23: 22 | B23: 202510 | C23: Trịnh Hà Phương | D23: SV10x12x26 | E23: 10A12 | F23: 0 | G23: 0 | H23: 0 | I23: 4 | J23: 0 | K23: 100000 | L23: =SUM(F23:J23) -> 4 | M23: =L23*K23 -> 400000 | N23: 400000 | P23: FT25300736359970 | S23: =M23-N23 -> 0 | T23: 0670190997777 | U23: NGUYEN THI HUYEN | V23: Ngân hàng MB
A24: 23 | B24: 202510 | C24: Đinh Hoài An | D24: SV10x12x13 | E24: 10A12 | F24: 6 | G24: 4 | H24: 0 | I24: 4 | J24: 0 | K24: 100000 | L24: =SUM(F24:J24) -> 14 | M24: =L24*K24 -> 1400000 | N24: =M24 -> 1400000 | P24: FT25298909530186 | S24: =M24-N24 -> 0 | T24: 0670190997777 | U24: NGUYEN THI HUYEN | V24: Ngân hàng MB
A25: 24 | B25: 202510 | C25: Trần Ngọc Anh | D25: SV10x12x14 | E25: 10A12 | F25: 0 | G25: 0 | H25: 0 | I25: 4 | J25: 0 | K25: 100000 | L25: =SUM(F25:J25) -> 4 | M25: =L25*K25 -> 400000 | N25: =M25 -> 400000 | P25: FT25296621805260 | S25: =M25-N25 -> 0 | T25: 0670190997777 | U25: NGUYEN THI HUYEN | V25: Ngân hàng MB
A26: 25 | B26: 202510 | C26: Phạm Khánh Chi | D26: SV10x12x15 | E26: 10A12 | F26: 0 | G26: 4 | H26: 0 | I26: 4 | J26: 0 | K26: 100000 | L26: =SUM(F26:J26) -> 8 | M26: =L26*K26 -> 800000 | N26: =M26 -> 800000 | P26: FT25300002988295 | S26: =M26-N26 -> 0 | T26: 0670190997777 | U26: NGUYEN THI HUYEN | V26: Ngân hàng MB
A27: 26 | B27: 202510 | C27: Nguyễn Hương Giang | D27: SV10x12x16 | E27: 10A12 | F27: 6 | G27: 4 | H27: 0 | I27: 4 | J27: 0 | K27: 100000 | L27: =SUM(F27:J27) -> 14 | M27: =L27*K27 -> 1400000 | N27: =M27 -> 1400000 | P27: FT25302905129929 | S27: =M27-N27 -> 0 | T27: 0670190997777 | U27: NGUYEN THI HUYEN | V27: Ngân hàng MB
A28: 27 | B28: 202510 | C28: Nguyễn Ngọc Hân | D28: SV10x12x17 | E28: 10A12 | F28: 6 | G28: 4 | H28: 0 | I28: 4 | J28: 0 | K28: 100000 | L28: =SUM(F28:J28) -> 14 | M28: =L28*K28 -> 1400000 | N28: =M28 -> 1400000 | P28: FT25295881609578 | S28: =M28-N28 -> 0 | T28: 0670190997777 | U28: NGUYEN THI HUYEN | V28: Ngân hàng MB
A29: 28 | B29: 202510 | C29: Đỗ Hoàng Ngọc Huyền | D29: SV10x12x18 | E29: 10A12 | F29: 0 | G29: 3 | H29: 0 | I29: 4 | J29: 0 | K29: 100000 | L29: =SUM(F29:J29) -> 7 | M29: =L29*K29 -> 700000 | N29: =M29 -> 700000 | P29: FT25293930329127 | S29: =M29-N29 -> 0 | T29: 0670190997777 | U29: NGUYEN THI HUYEN | V29: Ngân hàng MB
A30: 29 | B30: 202510 | C30: Lê Kiến Huy | D30: SV10x12x19 | E30: 10A12 | F30: 0 | G30: 4 | H30: 0 | I30: 4 | J30: 0 | K30: 100000 | L30: =SUM(F30:J30) -> 8 | M30: =L30*K30 -> 800000 | N30: =M30 -> 800000 | P30: FT25296365210421 | S30: =M30-N30 -> 0 | T30: 0670190997777 | U30: NGUYEN THI HUYEN | V30: Ngân hàng MB
A31: 30 | B31: 202510 | C31: Vũ Nguyễn Khánh An | D31: SV10x12x2 | E31: 10A12 | F31: 0 | G31: 4 | H31: 5 | I31: 0 | J31: 0 | K31: 100000 | L31: =SUM(F31:J31) -> 9 | M31: =L31*K31 -> 900000 | N31: =M31 -> 900000 | P31: FT25309150131183 | S31: =M31-N31 -> 0 | T31: 0670190997777 | U31: NGUYEN THI HUYEN | V31: Ngân hàng MB
A32: 31 | B32: 202510 | C32: Lã Bảo Khánh | D32: SV10x12x20 | E32: 10A12 | F32: 6 | G32: 4 | H32: 0 | I32: 4 | J32: 0 | K32: 100000 | L32: =SUM(F32:J32) -> 14 | M32: =L32*K32 -> 1400000 | N32: =M32 -> 1400000 | P32: FT25294032533499 | S32: =M32-N32 -> 0 | T32: 0670190997777 | U32: NGUYEN THI HUYEN | V32: Ngân hàng MB
A33: 32 | B33: 202510 | C33: Nguyễn Nam Khánh | D33: SV10x12x21 | E33: 10A12 | F33: 0 | G33: 4 | H33: 0 | I33: 4 | J33: 0 | K33: 100000 | L33: =SUM(F33:J33) -> 8 | M33: =L33*K33 -> 800000 | N33: =M33 -> 800000 | P33: FT25294027788217 | S33: =M33-N33 -> 0 | T33: 0670190997777 | U33: NGUYEN THI HUYEN | V33: Ngân hàng MB
A34: 33 | B34: 202510 | C34: Nguyễn Phương Linh | D34: SV10x12x22 | E34: 10A12 | F34: 6 | G34: 4 | H34: 0 | I34: 4 | J34: 0 | K34: 100000 | L34: =SUM(F34:J34) -> 14 | M34: =L34*K34 -> 1400000 | N34: =M34 -> 1400000 | P34: FT25295671611439 | S34: =M34-N34 -> 0 | T34: 0670190997777 | U34: NGUYEN THI HUYEN | V34: Ngân hàng MB
A35: 34 | B35: 202510 | C35: Lê Nguyễn Khánh Ly | D35: SV10x12x23 | E35: 10A12 | F35: 0 | G35: 0 | H35: 0 | I35: 4 | J35: 0 | K35: 100000 | L35: =SUM(F35:J35) -> 4 | M35: =L35*K35 -> 400000 | N35: =M35 -> 400000 | P35: FT25296364002445 | S35: =M35-N35 -> 0 | T35: 0670190997777 | U35: NGUYEN THI HUYEN | V35: Ngân hàng MB
... A46: 46 | B46: 202510 | C46: Chu Vĩnh Hưng | D46: SV10x12x34 | E46: 10A12 | F46: 6 | G46: 0 | H46: 0 | I46: 0 | J46: 0 | K46: 100000 | L46: =SUM(F46:J46) -> 6 | M46: =L46*K46 -> 600000 | N46: =M46 -> 600000 | P46: FT25300241877910 | S46: =M46-N46 -> 0 | T46: 0670190997777 | U46: NGUYEN THI HUYEN | V46: Ngân hàng MB
A47: 47 | B47: 202510 | C47: Mai Thái Sơn | D47: SV10x12x35 | E47: 10A12 | F47: 0 | G47: 0 | H47: 0 | I47: 0 | J47: 0 | K47: 100000 | L47: 0 | M47: =L47*K47 -> 0 | S47: =M47-N47 -> 0 | T47: 0670190997777 | U47: NGUYEN THI HUYEN | V47: Ngân hàng MB
A48: 48 | B48: 202510 | C48: Nguyễn Tùng Lâm | D48: SV10x12x36 | E48: 10A12 | F48: 0 | G48: 3 | H48: 0 | I48: 0 | J48: 0 | K48: 100000 | L48: =SUM(F48:J48) -> 3 | M48: =L48*K48 -> 300000 | N48: 300000 | P48: FT25293400131266 | S48: =M48-N48 -> 0 | T48: 0670190997777 | U48: NGUYEN THI HUYEN | V48: Ngân hàng MB
A49: 49 | B49: 202510 | C49: Hà Minh Đức | D49: SV10x12x4 | E49: 10A12 | F49: 0 | G49: 4 | H49: 5 | I49: 4 | J49: 0 | K49: 100000 | L49: =SUM(F49:J49) -> 13 | M49: =L49*K49 -> 1300000 | N49: =M49 -> 1300000 | P49: FT25293249491606 | S49: =M49-N49 -> 0 | T49: 0670190997777 | U49: NGUYEN THI HUYEN | V49: Ngân hàng MB
A50: 50 | B50: 202510 | C50: Bùi Phúc Hưng | D50: SV10x12x5 | E50: 10A12 | F50: 6 | G50: 4 | H50: 5 | I50: 4 | J50: 0 | K50: 100000 | L50: =SUM(F50:J50) -> 19 | M50: =L50*K50 -> 1900000 | N50: =M50 -> 1900000 | P50: FT25304836340440 | S50: =M50-N50 -> 0 | T50: 0670190997777 | U50: NGUYEN THI HUYEN | V50: Ngân hàng MB
A51: 51 | B51: 202510 | C51: Hoàng Trung Kiên | D51: SV10x12x6 | E51: 10A12 | F51: 6 | G51: 4 | H51: 5 | I51: 4 | J51: 0 | K51: 100000 | L51: =SUM(F51:J51) -> 19 | M51: =L51*K51 -> 1900000 | N51: =M51 -> 1900000 | P51: FT25298552186928 | S51: =M51-N51 -> 0 | T51: 0670190997777 | U51: NGUYEN THI HUYEN | V51: Ngân hàng MB
A52: 52 | B52: 202510 | C52: Ngô Duy Minh | D52: SV10x12x7 | E52: 10A12 | F52: 6 | G52: 4 | H52: 5 | I52: 4 | J52: 0 | K52: 100000 | L52: =SUM(F52:J52) -> 19 | M52: =L52*K52 -> 1900000 | N52: =M52 -> 1900000 | P52: FT25296882675103 | S52: =M52-N52 -> 0 | T52: 0670190997777 | U52: NGUYEN THI HUYEN | V52: Ngân hàng MB
A53: 53 | B53: 202510 | C53: Nguyễn Vũ Bảo Minh | D53: SV10x12x8 | E53: 10A12 | F53: 0 | G53: 0 | H53: 5 | I53: 4 | J53: 0 | K53: 100000 | L53: =SUM(F53:J53) -> 9 | M53: =L53*K53 -> 900000 | N53: =M53 -> 900000 | P53: FT25294145090776 | S53: =M53-N53 -> 0 | T53: 0670190997777 | U53: NGUYEN THI HUYEN | V53: Ngân hàng MB
A54: 54 | B54: 202510 | C54: Trần Bảo Minh | D54: SV10x12x9 | E54: 10A12 | F54: 6 | G54: 4 | H54: 5 | I54: 4 | J54: 0 | K54: 100000 | L54: =SUM(F54:J54) -> 19 | M54: =L54*K54 -> 1900000 | N54: =M54 -> 1900000 | P54: FT25297824724266 | S54: =M54-N54 -> 0 | T54: 0670190997777 | U54: NGUYEN THI HUYEN | V54: Ngân hàng MB
B55: 202510 | C55: Đỗ Trang Anh | D55: SV10x12x31 | E55: 10A12 | F55: 1 | G55: 0 | H55: 0 | I55: 1 | J55: 0 | K55: 100000 | L55: =SUM(F55:J55) -> 2 | M55: =L55*K55 -> 200000 | N55: =M55 -> 200000 | P55: FT25303080086478 | S55: =M55-N55 -> 0 | T55: 0670190997777 | U55: NGUYEN THI HUYEN | V55: Ngân hàng MB
B56: 202510 | C56: Đỗ Thị Quế Phương | D56: SV10x12x13 | E56: 10A12 | F56: 0 | G56: 2 | H56: 4 | I56: 0 | J56: 0 | K56: 100000 | L56: =SUM(F56:J56) -> 6 | M56: =L56*K56 -> 600000 | N56: =M56 -> 600000 | P56: FT25304264764875 | S56: =M56-N56 -> 0 | T56: 0670190997777 | U56: NGUYEN THI HUYEN | V56: Ngân hàng MB
A57: 55 | B57: 202510 | C57: Đỗ Thị Vân Hà | D57: SV10x13x1 | E57: 10A13 | F57: 0 | G57: 0 | H57: 3 | I57: 0 | J57: 0 | K57: 100000 | L57: =SUM(F57:J57) -> 3 | M57: =L57*K57 -> 300000 | N57: =M57 -> 300000 | P57: FT25297077435088 | S57: =M57-N57 -> 0 | T57: 0670190997777 | U57: NGUYEN THI HUYEN | V57: Ngân hàng MB
A58: 56 | B58: 202510 | C58: Vũ Xuân Trường | D58: SV10x13x10 | E58: 10A13 | F58: 0 | G58: 0 | H58: 4 | I58: 0 | J58: 0 | K58: 100000 | L58: =SUM(F58:J58) -> 4 | M58: =L58*K58 -> 400000 | N58: =M58 -> 400000 | P58: FT25295100048588 | S58: =M58-N58 -> 0 | T58: 0670190997777 | U58: NGUYEN THI HUYEN | V58: Ngân hàng MB
A59: 57 | B59: 202510 | C59: Nguyễn Thanh Tùng | D59: SV10x13x11 | E59: 10A13 | F59: 0 | G59: 0 | H59: 4 | I59: 0 | J59: 0 | K59: 100000 | L59: =SUM(F59:J59) -> 4 | M59: =L59*K59 -> 400000 | N59: =M59 -> 400000 | P59: FT25300102201762 | S59: =M59-N59 -> 0 | T59: 0670190997777 | U59: NGUYEN THI HUYEN | V59: Ngân hàng MB
A60: 58 | B60: 202510 | C60: Phạm Hà Phương Uyên | D60: SV10x13x12 | E60: 10A13 | F60: 0 | G60: 0 | H60: 4 | I60: 0 | J60: 0 | K60: 100000 | L60: =SUM(F60:J60) -> 4 | M60: =L60*K60 -> 400000 | N60: =M60 -> 400000 | P60: FT25300032498381 | S60: =M60-N60 -> 0 | T60: 0670190997777 | U60: NGUYEN THI HUYEN | V60: Ngân hàng MB
A61: 59 | B61: 202510 | C61: Đỗ Thanh Vinh | D61: SV10x13x13 | E61: 10A13 | F61: 0 | G61: 0 | H61: 3 | I61: 0 | J61: 0 | K61: 100000 | L61: =SUM(F61:J61) -> 3 | M61: =L61*K61 -> 300000 | N61: =M61 -> 300000 | P61: FT25297956011135 | S61: =M61-N61 -> 0 | T61: 0670190997777 | U61: NGUYEN THI HUYEN | V61: Ngân hàng MB
A62: 60 | B62: 202510 | C62: Nguyễn Phương Vy | D62: SV10x13x14 | E62: 10A13 | F62: 0 | G62: 0 | H62: 4 | I62: 0 | J62: 0 | K62: 100000 | L62: =SUM(F62:J62) -> 4 | M62: =L62*K62 -> 400000 | N62: =M62 -> 400000 | P62: FT25297048068470 | S62: =M62-N62 -> 0 | T62: 0670190997777 | U62: NGUYEN THI HUYEN | V62: Ngân hàng MB
A63: 61 | B63: 202510 | C63: Nguyễn Thảo Xuân | D63: SV10x13x15 | E63: 10A13 | F63: 0 | G63: 0 | H63: 4 | I63: 0 | J63: 0 | K63: 100000 | L63: =SUM(F63:J63) -> 4 | M63: =L63*K63 -> 400000 | N63: =M63+200000 -> 600000 | P63: FT25308940819220 FT25308057474686 | S63: =M63-N63 -> -200000 | T63: 0670190997777 | U63: NGUYEN THI HUYEN | V63: Ngân hàng MB
A64: 62 | B64: 202510 | C64: Nguyễn Huy Hoàng | D64: SV10x13x2 | E64: 10A13 | F64: 0 | G64: 0 | H64: 4 | I64: 0 | J64: 0 | K64: 100000 | L64: =SUM(F64:J64) -> 4 | M64: =L64*K64 -> 400000 | N64: =M64 -> 400000 | P64: FT25295094098407 | S64: =M64-N64 -> 0 | T64: 0670190997777 | U64: NGUYEN THI HUYEN | V64: Ngân hàng MB
A65: 63 | B65: 202510 | C65: Lê Gia Linh | D65: SV10x13x3 | E65: 10A13 | F65: 0 | G65: 0 | H65: 4 | I65: 0 | J65: 0 | K65: 100000 | L65: =SUM(F65:J65) -> 4 | M65: =L65*K65 -> 400000 | N65: =M65 -> 400000 | P65: FT25296800106248 | S65: =M65-N65 -> 0 | T65: 0670190997777 | U65: NGUYEN THI HUYEN | V65: Ngân hàng MB
A66: 65 | B66: 202510 | C66: Phạm Ngọc Mến | D66: SV10x13x5 | E66: 10A13 | F66: 0 | G66: 0 | H66: 4 | I66: 0 | J66: 0 | K66: 100000 | L66: =SUM(F66:J66) -> 4 | M66: =L66*K66 -> 400000 | N66: =M66 -> 400000 | P66: FT25300560141039 | S66: =M66-N66 -> 0 | T66: 0670190997777 | U66: NGUYEN THI HUYEN | V66: Ngân hàng MB
A67: 66 | B67: 202510 | C67: Khúc Nguyễn Hà My | D67: SV10x13x6 | E67: 10A13 | F67: 0 | G67: 0 | H67: 4 | I67: 0 | J67: 0 | K67: 100000 | L67: =SUM(F67:J67) -> 4 | M67: =L67*K67 -> 400000 | N67: =M67 -> 400000 | P67: FT25295935727846 | S67: =M67-N67 -> 0 | T67: 0670190997777 | U67: NGUYEN THI HUYEN | V67: Ngân hàng MB
A68: 67 | B68: 202510 | C68: Trần Diệu My | D68: SV10x13x7 | E68: 10A13 | F68: 0 | G68: 0 | H68: 4 | I68: 0 | J68: 0 | K68: 100000 | L68: =SUM(F68:J68) -> 4 | M68: =L68*K68 -> 400000 | N68: =M68 -> 400000 | P68: FT25300080899780 | S68: =M68-N68 -> 0 | T68: 0670190997777 | U68: NGUYEN THI HUYEN | V68: Ngân hàng MB
A69: 68 | B69: 202510 | C69: Lê Bích Tâm | D69: SV10x13x8 | E69: 10A13 | F69: 0 | G69: 0 | H69: 4 | I69: 0 | J69: 0 | K69: 100000 | L69: =SUM(F69:J69) -> 4 | M69: =L69*K69 -> 400000 | N69: =M69 -> 400000 | P69: FT25293925814319 | S69: =M69-N69 -> 0 | T69: 0670190997777 | U69: NGUYEN THI HUYEN | V69: Ngân hàng MB
A70: 69 | B70: 202510 | C70: Dương Xuân Trang | D70: SV10x13x9 | E70: 10A13 | F70: 0 | G70: 0 | H70: 4 | I70: 0 | J70: 0 | K70: 100000 | L70: =SUM(F70:J70) -> 4 | M70: =L70*K70 -> 400000 | N70: =M70 -> 400000 | P70: FT25300310063060 | S70: =M70-N70 -> 0 | T70: 0670190997777 | U70: NGUYEN THI HUYEN | V70: Ngân hàng MB
A71: 70 | B71: 202510 | C71: Bùi Thị Mai Anh | D71: SV10x14x1 | E71: 10A14 | F71: 0 | G71: 0 | H71: 5 | I71: 0 | J71: 0 | K71: 100000 | L71: =SUM(F71:J71) -> 5 | M71: =L71*K71 -> 500000 | N71: =M71 -> 500000 | P71: FT25294762255782 | S71: =M71-N71 -> 0 | T71: 0670190997777 | U71: NGUYEN THI HUYEN | V71: Ngân hàng MB
A72: 71 | B72: 202510 | C72: Nguyễn Tuấn Phong | D72: SV10x14x10 | E72: 10A14 | F72: 0 | G72: 0 | H72: 5 | I72: 0 | J72: 0 | K72: 100000 | L72: =SUM(F72:J72) -> 5 | M72: =L72*K72 -> 500000 | N72: =M72 -> 500000 | P72: FT25302340164202 | S72: =M72-N72 -> 0 | T72: 0670190997777 | U72: NGUYEN THI HUYEN | V72: Ngân hàng MB
A73: 72 | B73: 202510 | C73: Lưu Minh Phương | D73: SV10x14x11 | E73: 10A14 | F73: 4 | G73: 0 | H73: 5 | I73: 4 | J73: 0 | K73: 100000 | L73: =SUM(F73:J73) -> 13 | M73: =L73*K73 -> 1300000 | N73: =M73 -> 1300000 | P73: FT25300439099040 | S73: =M73-N73 -> 0 | T73: 0670190997777 | U73: NGUYEN THI HUYEN | V73: Ngân hàng MB
A74: 73 | B74: 202510 | C74: Nguyễn Minh Quân | D74: SV10x14x12 | E74: 10A14 | F74: 0 | G74: 3 | H74: 0 | I74: 0 | J74: 0 | K74: 100000 | L74: =SUM(F74:J74) -> 3 | M74: =L74*K74 -> 300000 | R74: Lụa Văn 3 | S74: =M74-N74 -> 300000 | T74: 0670190997777 | U74: NGUYEN THI HUYEN | V74: Ngân hàng MB
A75: 74 | B75: 202510 | C75: Bùi Phương Thảo | D75: SV10x14x13 | E75: 10A14 | F75: 4 | G75: 0 | H75: 5 | I75: 4 | J75: 0 | K75: 100000 | L75: =SUM(F75:J75) -> 13 | M75: =L75*K75 -> 1300000 | N75: =M75 -> 1300000 | P75: FT25309210450052 | S75: =M75-N75 -> 0 | T75: 0670190997777 | U75: NGUYEN THI HUYEN | V75: Ngân hàng MB
A76: 75 | B76: 202510 | C76: Trần Quốc Bảo | D76: SV10x14x14 | E76: 10A14 | F76: 0 | G76: 0 | H76: 0 | I76: 0 | J76: 0 | K76: 100000 | L76: =SUM(F76:J76) -> 0 | M76: =L76*K76 -> 0 | S76: =M76-N76 -> 0 | T76: 0670190997777 | U76: NGUYEN THI HUYEN | V76: Ngân hàng MB
A77: 76 | B77: 202510 | C77: Nguyễn Phương Nhi | D77: SV10x14x15 | E77: 10A14 | F77: 4 | G77: 3 | H77: 0 | I77: 4 | J77: 0 | K77: 100000 | L77: =SUM(F77:J77) -> 11 | M77: =L77*K77 -> 1100000 | N77: =M77 -> 1100000 | P77: FT25297957503751 | S77: =M77-N77 -> 0 | T77: 0670190997777 | U77: NGUYEN THI HUYEN | V77: Ngân hàng MB
A78: 77 | B78: 202510 | C78: Đặng Thế Quang | D78: SV10x14x16 | E78: 10A14 | F78: 4 | G78: 3 | H78: 0 | I78: 4 | J78: 0 | K78: 100000 | L78: =SUM(F78:J78) -> 11 | M78: =L78*K78 -> 1100000 | N78: =M78 -> 1100000 | P78: FT25307808554781 | S78: =M78-N78 -> 0 | T78: 0670190997777 | U78: NGUYEN THI HUYEN | V78: Ngân hàng MB
A79: 78 | B79: 202510 | C79: Nguyễn Hoàng Sơn | D79: SV10x14x17 | E79: 10A14 | F79: 4 | G79: 3 | H79: 0 | I79: 4 | J79: 0 | K79: 100000 | L79: =SUM(F79:J79) -> 11 | M79: =L79*K79 -> 1100000 | N79: =M79 -> 1100000 | P79: FT25308105213460 | S79: =M79-N79 -> 0 | T79: 0670190997777 | U79: NGUYEN THI HUYEN | V79: Ngân hàng MB
A80: 79 | B80: 202510 | C80: Nguyễn Duy Toàn | D80: SV10x14x18 | E80: 10A14 | F80: 4 | G80: 3 | H80: 0 | I80: 4 | J80: 0 | K80: 100000 | L80: =SUM(F80:J80) -> 11 | M80: =L80*K80 -> 1100000 | N80: =M80 -> 1100000 | P80: FT25305210040410 | S80: =M80-N80 -> 0 | T80: 0670190997777 | U80: NGUYEN THI HUYEN | V80: Ngân hàng MB
A81: 80 | B81: 202510 | C81: Vũ Đức Thiện | D81: SV10x14x19 | E81: 10A14 | F81: 4 | G81: 3 | H81: 0 | I81: 4 | J81: 0 | K81: 100000 | L81: =SUM(F81:J81) -> 11 | M81: =L81*K81 -> 1100000 | N81: =M81 -> 1100000 | P81: FT25303960614855 | S81: =M81-N81 -> 0 | T81: 0670190997777 | U81: NGUYEN THI HUYEN | V81: Ngân hàng MB
A82: 81 | B82: 202510 | C82: Mai Trường Giang | D82: SV10x14x2 | E82: 10A14 | F82: 0 | G82: 0 | H82: 5 | I82: 0 | J82: 0 | K82: 100000 | L82: =SUM(F82:J82) -> 5 | M82: =L82*K82 -> 500000 | N82: =M82 -> 500000 | P82: FT25310091500601 | S82: =M82-N82 -> 0 | T82: 0670190997777 | U82: NGUYEN THI HUYEN | V82: Ngân hàng MB
A83: 82 | B83: 202510 | C83: Nguyễn Phương Anh | D83: SV10x14x20 | E83: 10A14 | F83: 4 | G83: 0 | H83: 0 | I83: 0 | J83: 0 | K83: 100000 | L83: =SUM(F83:J83) -> 4 | M83: =L83*K83 -> 400000 | N83: =M83 -> 400000 | P83: FT25309140205867 | S83: =M83-N83 -> 0 | T83: 0670190997777 | U83: NGUYEN THI HUYEN | V83: Ngân hàng MB
A84: 83 | B84: 202510 | C84: Ngô Tiến Đạt | D84: SV10x14x21 | E84: 10A14 | F84: 4 | G84: 3 | H84: 0 | I84: 0 | J84: 0 | K84: 100000 | L84: =SUM(F84:J84) -> 7 | M84: =L84*K84 -> 700000 | N84: =M84 -> 700000 | P84: FT25303044008011 | S84: =M84-N84 -> 0 | T84: 0670190997777 | U84: NGUYEN THI HUYEN | V84: Ngân hàng MB
A85: 85 | B85: 202510 | C85: Nguyễn Hải Ngọc Hân | D85: SV10x14x3 | E85: 10A14 | F85: 4 | G85: 0 | H85: 5 | I85: 4 | J85: 0 | K85: 100000 | L85: =SUM(F85:J85) -> 13 | M85: =L85*K85 -> 1300000 | N85: =M85 -> 1300000 | P85: FT25295682275694 | S85: =M85-N85 -> 0 | T85: 0670190997777 | U85: NGUYEN THI HUYEN | V85: Ngân hàng MB
A86: 86 | B86: 202510 | C86: Hoàng Trí Hiền | D86: SV10x14x4 | E86: 10A14 | F86: 4 | G86: 3 | H86: 5 | I86: 4 | J86: 0 | K86: 100000 | L86: =SUM(F86:J86) -> 16 | M86: =L86*K86 -> 1600000 | N86: =M86 -> 1600000 | P86: FT25304590021483 | S86: =M86-N86 -> 0 | T86: 0670190997777 | U86: NGUYEN THI HUYEN | V86: Ngân hàng MB
A87: 87 | B87: 202510 | C87: Nguyễn Thị Ngọc Khánh | D87: SV10x14x5 | E87: 10A14 | F87: 4 | G87: 3 | H87: 5 | I87: 0 | J87: 0 | K87: 100000 | L87: =SUM(F87:J87) -> 12 | M87: =L87*K87 -> 1200000 | N87: =M87 -> 1200000 | P87: FT25302760209762 | S87: =M87-N87 -> 0 | T87: 0670190997777 | U87: NGUYEN THI HUYEN | V87: Ngân hàng MB
A88: 88 | B88: 202510 | C88: Đinh Lê Phương Linh | D88: SV10x14x6 | E88: 10A14 | F88: 4 | G88: 3 | H88: 5 | I88: 4 | J88: 0 | K88: 100000 | L88: =SUM(F88:J88) -> 16 | M88: =L88*K88 -> 1600000 | N88: =M88 -> 1600000 | P88: FT25301090001507 | S88: =M88-N88 -> 0 | T88: 0670190997777 | U88: NGUYEN THI HUYEN | V88: Ngân hàng MB
... A91: 91 | B91: 202510 | C91: Trần Yến Nhi | D91: SV10x14x9 | E91: 10A14 | F91: 4 | G91: 0 | H91: 5 | I91: 0 | J91: 0 | K91: 100000 | L91: =SUM(F91:J91) -> 9 | M91: =L91*K91 -> 900000 | N91: =M91 -> 900000 | P91: FT25310268801899 | S91: =M91-N91 -> 0 | T91: 0670190997777 | U91: NGUYEN THI HUYEN | V91: Ngân hàng MB
B92: 202510 | C92: Lưu Tường An | D92: SV10x16x1 | E92: 10A16 | F92: 5 | G92: 0 | H92: 5 | I92: 0 | J92: 0 | K92: 100000 | L92: =SUM(F92:J92) -> 10 | M92: =L92*K92 -> 1000000 | N92: =M92 -> 1000000 | P92: FT25297321011980 | S92: =M92-N92 -> 0 | T92: 0670190997777 | U92: NGUYEN THI HUYEN | V92: Ngân hàng MB
B93: 202510 | C93: Nguyễn Nam Khánh | D93: SV10x16x10 | E93: 10A16 | F93: 0 | G93: 0 | H93: 4 | I93: 0 | J93: 0 | K93: 100000 | L93: =SUM(F93:J93) -> 4 | M93: =L93*K93 -> 400000 | N93: =M93 -> 400000 | P93: FT25304701470570 | S93: =M93-N93 -> 0 | T93: 0670190997777 | U93: NGUYEN THI HUYEN | V93: Ngân hàng MB
B94: 202510 | C94: Ngô Gia Lộc | D94: SV10x16x11 | E94: 10A16 | F94: 0 | G94: 0 | H94: 5 | I94: 0 | J94: 0 | K94: 100000 | L94: =SUM(F94:J94) -> 5 | M94: =L94*K94 -> 500000 | N94: =M94 -> 500000 | P94: FT25302118479807 | S94: =M94-N94 -> 0 | T94: 0670190997777 | U94: NGUYEN THI HUYEN | V94: Ngân hàng MB
B95: 202510 | C95: Đỗ Khánh Ly | D95: SV10x16x12 | E95: 10A16 | F95: 0 | G95: 0 | H95: 5 | I95: 0 | J95: 0 | K95: 100000 | L95: =SUM(F95:J95) -> 5 | M95: =L95*K95 -> 500000 | N95: =M95 -> 500000 | P95: FT25304780803145 | S95: =M95-N95 -> 0 | T95: 0670190997777 | U95: NGUYEN THI HUYEN | V95: Ngân hàng MB
B96: 202510 | C96: Hồ Hải Nam | D96: SV10x16x13 | E96: 10A16 | F96: 4 | G96: 0 | H96: 4 | I96: 0 | J96: 0 | K96: 100000 | L96: =SUM(F96:J96) -> 8 | M96: =L96*K96 -> 800000 | N96: =M96 -> 800000 | P96: FT25303038662793 | S96: =M96-N96 -> 0 | T96: 0670190997777 | U96: NGUYEN THI HUYEN | V96: Ngân hàng MB
B97: 202510 | C97: Lê Hoàng Nam | D97: SV10x16x14 | E97: 10A16 | F97: 5 | G97: 0 | H97: 5 | I97: 0 | J97: 0 | K97: 100000 | L97: =SUM(F97:J97) -> 10 | M97: =L97*K97 -> 1000000 | N97: =M97 -> 1000000 | P97: FT25302286120795 | S97: =M97-N97 -> 0 | T97: 0670190997777 | U97: NGUYEN THI HUYEN | V97: Ngân hàng MB
B98: 202510 | C98: Đoàn Nam Phong | D98: SV10x16x15 | E98: 10A16 | F98: 0 | G98: 0 | H98: 5 | I98: 0 | J98: 0 | K98: 100000 | L98: =SUM(F98:J98) -> 5 | M98: =L98*K98 -> 500000 | N98: =M98 -> 500000 | P98: FT25304083891100 | S98: =M98-N98 -> 0 | T98: 0670190997777 | U98: NGUYEN THI HUYEN | V98: Ngân hàng MB
B99: 202510 | C99: Hà Thị Mai Phương | D99: SV10x16x16 | E99: 10A16 | F99: 4 | G99: 0 | H99: 5 | I99: 0 | J99: 0 | K99: 100000 | L99: =SUM(F99:J99) -> 9 | M99: =L99*K99 -> 900000 | N99: =500000+400000 -> 900000 | P99: FT25295244404410 FT25302365060934 | S99: =M99-N99 -> 0 | T99: 0670190997777 | U99: NGUYEN THI HUYEN | V99: Ngân hàng MB
B100: 202510 | C100: Nguyễn Minh Quân | D100: SV10x16x17 | E100: 10A16 | F100: 0 | G100: 0 | H100: 5 | I100: 0 | J100: 0 | K100: 100000 | L100: =SUM(F100:J100) -> 5 | M100: =L100*K100 -> 500000 | N100: =M100 -> 500000 | P100: FT25302305262776 | S100: =M100-N100 -> 0 | T100: 0670190997777 | U100: NGUYEN THI HUYEN | V100: Ngân hàng MB
B101: 202510 | C101: Nguyễn Vũ Anh Quân | D101: SV10x16x18 | E101: 10A16 | F101: 0 | G101: 0 | H101: 5 | I101: 0 | J101: 0 | K101: 100000 | L101: =SUM(F101:J101) -> 5 | M101: =L101*K101 -> 500000 | N101: =M101 -> 500000 | P101: FT25303147594658 | S101: =M101-N101 -> 0 | T101: 0670190997777 | U101: NGUYEN THI HUYEN | V101: Ngân hàng MB
B102: 202510 | C102: Nguyễn Xuân Sáng | D102: SV10x16x19 | E102: 10A16 | F102: 0 | G102: 0 | H102: 5 | I102: 0 | J102: 0 | K102: 100000 | L102: =SUM(F102:J102) -> 5 | M102: =L102*K102 -> 500000 | N102: =M102 -> 500000 | P102: FT25303802800504 | S102: =M102-N102 -> 0 | T102: 0670190997777 | U102: NGUYEN THI HUYEN | V102: Ngân hàng MB
B103: 202510 | C103: Vũ Khánh An | D103: SV10x16x2 | E103: 10A16 | F103: 5 | G103: 0 | H103: 5 | I103: 0 | J103: 0 | K103: 100000 | L103: =SUM(F103:J103) -> 10 | M103: =L103*K103 -> 1000000 | N103: =M103 -> 1000000 | P103: FT25302575337536 | S103: =M103-N103 -> 0 | T103: 0670190997777 | U103: NGUYEN THI HUYEN | V103: Ngân hàng MB
B104: 202510 | C104: Nguyễn Thị Minh Thư | D104: SV10x16x20 | E104: 10A16 | F104: 5 | G104: 0 | H104: 5 | I104: 0 | J104: 0 | K104: 100000 | L104: =SUM(F104:J104) -> 10 | M104: =L104*K104 -> 1000000 | N104: =M104+500000 -> 1500000 | P104: FT25300291035161 FT25304603601803 | S104: =M104-N104 -> -500000 | T104: 0670190997777 | U104: NGUYEN THI HUYEN | V104: Ngân hàng MB
B105: 202510 | C105: Tống Trâm Anh | D105: SV10x16x21 | E105: 10A16 | F105: 5 | G105: 0 | H105: 0 | I105: 0 | J105: 0 | K105: 100000 | L105: =SUM(F105:J105) -> 5 | M105: =L105*K105 -> 500000 | N105: =M105 -> 500000 | P105: FT25302937601001 | S105: =M105-N105 -> 0 | T105: 0670190997777 | U105: NGUYEN THI HUYEN | V105: Ngân hàng MB
B106: 202510 | C106: Đoàn Thủy Bích | D106: SV10x16x22 | E106: 10A16 | F106: 3 | G106: 0 | H106: 0 | I106: 0 | J106: 0 | K106: 100000 | L106: =SUM(F106:J106) -> 3 | M106: =L106*K106 -> 300000 | N106: =M106 -> 300000 | P106: FT25304260224902 | S106: =M106-N106 -> 0 | T106: 0670190997777 | U106: NGUYEN THI HUYEN | V106: Ngân hàng MB
B107: 202510 | C107: Nguyễn Huy Khánh | D107: SV10x16x23 | E107: 10A16 | F107: 5 | G107: 0 | H107: 0 | I107: 0 | J107: 0 | K107: 100000 | L107: =SUM(F107:J107) -> 5 | M107: =L107*K107 -> 500000 | N107: =M107 -> 500000 | P107: FT25301400176730 | S107: =M107-N107 -> 0 | T107: 0670190997777 | U107: NGUYEN THI HUYEN | V107: Ngân hàng MB
B108: 202510 | C108: Đỗ Ngọc Bảo Linh | D108: SV10x16x24 | E108: 10A16 | F108: 4 | G108: 0 | H108: 0 | I108: 0 | J108: 0 | K108: 100000 | L108: =SUM(F108:J108) -> 4 | M108: =L108*K108 -> 400000 | N108: =M108 -> 400000 | P108: FT25300270218902 | S108: =M108-N108 -> 0 | T108: 0670190997777 | U108: NGUYEN THI HUYEN | V108: Ngân hàng MB
B109: 202510 | C109: Đào Trần Anh Minh | D109: SV10x16x25 | E109: 10A16 | F109: 5 | G109: 0 | H109: 0 | I109: 0 | J109: 0 | K109: 100000 | L109: =SUM(F109:J109) -> 5 | M109: =L109*K109 -> 500000 | N109: =M109 -> 500000 | P109: FT25302815293369 | S109: =M109-N109 -> 0 | T109: 0670190997777 | U109: NGUYEN THI HUYEN | V109: Ngân hàng MB
B110: 202510 | C110: Phạm Gia Minh | D110: SV10x16x26 | E110: 10A16 | F110: 4 | G110: 0 | H110: 0 | I110: 0 | J110: 0 | K110: 100000 | L110: =SUM(F110:J110) -> 4 | M110: =L110*K110 -> 400000 | N110: =M110 -> 400000 | P110: FT25302078342453 | S110: =M110-N110 -> 0 | T110: 0670190997777 | U110: NGUYEN THI HUYEN | V110: Ngân hàng MB
B111: 202510 | C111: Nguyễn Sỹ Nguyên | D111: SV10x16x27 | E111: 10A16 | F111: 5 | G111: 0 | H111: 0 | I111: 0 | J111: 0 | K111: 100000 | L111: =SUM(F111:J111) -> 5 | M111: =L111*K111 -> 500000 | N111: =M98 -> 500000 | P111: FT25295328515789 | S111: =M111-N111 -> 0 | T111: 0670190997777 | U111: NGUYEN THI HUYEN | V111: Ngân hàng MB
B112: 202510 | C112: Vũ Nguyễn Văn Quân | D112: SV10x16x28 | E112: 10A16 | F112: 5 | G112: 0 | H112: 0 | I112: 0 | J112: 0 | K112: 100000 | L112: =SUM(F112:J112) -> 5 | M112: =L112*K112 -> 500000 | N112: =M112 -> 500000 | P112: FT25300682066539 | S112: =M112-N112 -> 0 | T112: 0670190997777 | U112: NGUYEN THI HUYEN | V112: Ngân hàng MB
B113: 202510 | C113: Nguyễn Minh Anh | D113: SV10x16x3 | E113: 10A16 | F113: 0 | G113: 0 | H113: 5 | I113: 0 | J113: 0 | K113: 100000 | L113: =SUM(F113:J113) -> 5 | M113: =L113*K113 -> 500000 | N113: =M113 -> 500000 | P113: FT25304474060808 | S113: =M113-N113 -> 0 | T113: 0670190997777 | U113: NGUYEN THI HUYEN | V113: Ngân hàng MB
B114: 202510 | C114: Vũ Hà Anh | D114: SV10x16x4 | E114: 10A16 | F114: 4 | G114: 0 | H114: 5 | I114: 0 | J114: 0 | K114: 100000 | L114: =SUM(F114:J114) -> 9 | M114: =L114*K114 -> 900000 | N114: =M114 -> 900000 | P114: FT25304583620784 | S114: =M114-N114 -> 0 | T114: 0670190997777 | U114: NGUYEN THI HUYEN | V114: Ngân hàng MB
B115: 202510 | C115: Nguyễn Khánh Chi | D115: SV10x16x5 | E115: 10A16 | F115: 5 | G115: 0 | H115: 5 | I115: 0 | J115: 0 | K115: 100000 | L115: =SUM(F115:J115) -> 10 | M115: =L115*K115 -> 1000000 | N115: =M115 -> 1000000 | P115: FT25300597060069 | S115: =M115-N115 -> 0 | T115: 0670190997777 | U115: NGUYEN THI HUYEN | V115: Ngân hàng MB
...

Sheet CT
F1: SAO KÊ CHI TIẾT TÀI KHOẢN Account Statement | O1: NGÂN HÀNG TMCP QUÂN ĐỘI Military Commercial Joint Stock Bank
F2: Từ ngày/From:15/10/2025 00:00:00 Đến ngày/To:23/10/2025 23:59:59 | O2: Chi nhánh/Branch: VN0010060 - Dong Ha Noi
A4: Tên khách hàng/Customer name: CONG TY TNHH TRI THUC SAO VIET Mã khách hàng/Customer code: 37285976 Địa chỉ/Address: SO 5 HEM 197/318/7 DUONG THACH BAN-PHUONG THACH BAN-QUAN LONG BIEN-THANH PHO HA NOI-VIET NAM | Q4: Tài khoản/Account No: 2588666868 Mã số thuế/Tax code: 0110940616 Loại tiền/Currency: VND
C6: Chúng tôi xin thông báo chi tiết phát sinh nợ/có trên tài khoản quý khách trong thời gian trên như sau: We would like to inform you about your account debit/credit transactions as the following details: Số dư đầu kỳ/ Opening Balance: 78,946,894 VND
A7: STT | D7: NGÀY GIAO DỊCH | G7: NGÀY HẠCH TOÁN | H7: PHÁT SINH NỢ | I7: PHÁT SINH CÓ | J7: SỐ DƯ | L7: ĐƠN VỊ THỤ HƯỞNG/ĐƠN VỊ CHUYỂN | M7: NỘI DUNG | R7: BÚT TOÁN
A8: 1 | D8: 10/11/2025 19:31:47 | G8: 10/11/2025 | H8: 0 | I8: 1,400,000 | J8: 75,222,160 | L8: SHBMB | M8: Luu Tram Anh SV12x3x1 thang 10 Ma giao dich Trace463192 Trace 46319 | R8: FT25314653040894
A9: 3 | D9: 07/11/2025 07:51:50 | G9: 07/11/2025 | H9: 0 | I9: 900,000 | J9: 246,308,960 | L9: PHAM THI THANH THUY | M9: Nguyen An Phuong SV12x2x31 thang 10 | R9: FT25311405411089
A10: 1 | D10: 06/11/2025 20:03:17 | G10: 06/11/2025 | H10: 0 | I10: 2,600,000 | J10: 245,408,960 | L10: NGUYEN NGOC LAN | M10: MBVCB.11613275362.813368.Nguyen Duc Minh SV12x3x34 thang 10.CT tu 9358 832572 NGUYEN NGOC LAN toi 25886668 68 CONG TY TNHH TRI THUC SAO VIET t ai MB- Ma GD ACSP/ hb813368 | R10: FT25310200056333
A11: 1 | D11: 05/11/2025 21:57:54 | G11: 05/11/2025 | H11: 0 | I11: 900,000 | J11: 242,808,960 | L11: VND-TGTT-BUI THI KIM OANH | M11: Nguyen Bui Minh Duc SV11x3x25 thang 10 FT25310088398630 Ma giao dich Trace530832 Trace 530832 | R11: FT25309710796213
A12: 1 | D12: 05/11/2025 19:56:18 | G12: 05/11/2025 | H12: 0 | I12: 800,000 | J12: 241,908,960 | L12: LUONG HA THANH | M12: Lai Duc Khanh SV12x6x25 thang 10 | R12: FT25309423040360
A13: 2 | D13: 05/11/2025 18:47:34 | G13: 05/11/2025 | H13: 0 | I13: 700,000 | J13: 241,108,960 | L13: LE THI THUY DUONG | M13: Ho Duc Viet SV12x6x22 thang 10 FT25 309904680821 Ma giao dich Trace3 23956 Trace 323956 | R13: FT25309333190597
A14: 1 | D14: 04/11/2025 23:26:59 | G14: 05/11/2025 | H14: 0 | I14: 900,000 | J14: 240,408,960 | L14: VND-TGTT-NGUYEN THANH HANG | M14: Hoang Minh Huy SV12x2x7 thang 10 FT 25309750063262 Ma giao dich Trac e358271 Trace 358271 | R14: FT25309015020433
A15: 2 | D15: 04/11/2025 22:04:37 | G15: 05/11/2025 | H15: 0 | I15: 1,800,000 | J15: 239,508,960 | L15: NGUYEN VAN KIEU | M15: VO QUANG MINH SV12X2X25 THANG 10- M a GD ACSP/ WV195701 | R15: FT25309847961096
A16: 3 | D16: 04/11/2025 21:43:08 | G16: 04/11/2025 | H16: 0 | I16: 900,000 | J16: 237,708,960 | L16: NGUYEN TRUONG SON | M16: NGUYEN NGOC ANH SV12X2X35 THANG 10- Ma GD ACSP/ 2b095573 | R16: FT25308316553593
A17: 4 | D17: 04/11/2025 21:00:54 | G17: 04/11/2025 | H17: 0 | I17: 900,000 | J17: 236,808,960 | L17: PHAN VAN THANG | M17: Phan Truong Giang SV12x2x28 thang 1 0 | R17: FT25308259278932
A18: 5 | D18: 04/11/2025 20:55:07 | G18: 04/11/2025 | H18: 0 | I18: 1,800,000 | J18: 235,908,960 | L18: HO KINH DOANH THY HUONG | M18: QR Nguyen Minh Quan SV12x2x24 tha ng 10- Ma GD ACSP/ br659732 | R18: FT25308064027205
... A41: 21 | D41: 30/10/2025 21:00:31 | G41: 30/10/2025 | H41: 0 | I41: 2,700,000 | J41: 211,548,381 | L41: MAI THI THANH QUYNH | M41: MBVCB.11518187411.397232.Do Thu Hie n SV12x1x8 TT hoc them T10 .CT tu 0 021000321578 MAI THI THANH QUYNH to i 2588666868 CONG TY TNHH TRI THUC SAO VIET tai MB- Ma GD ACSP/ fu397232 | R41: FT25303094555430
A42: 22 | D42: 30/10/2025 19:03:38 | G42: 30/10/2025 | H42: 0 | I42: 900,000 | J42: 208,848,381 | L42: CONG TY CO PHAN ZION | M42: ZALOPAY-CHUYENTIEN-O5CH7BKSPCLU-con The Anh dong tien hoc | R42: FT25303048630587 | U42: SV12x5x31
A43: 23 | D43: 30/10/2025 13:01:14 | G43: 30/10/2025 | H43: 0 | I43: 1,300,000 | J43: 207,948,381 | L43: LE VAN KHOA | M43: MBVCB.11511851679.229561.LE Thai D uy SV12x5x5 thang 10.CT tu 00210010 29533 LE VAN KHOA toi 2588666868 CO NG TY TNHH TRI THUC SAO VIET tai MB - Ma GD ACSP/ ce229561 | R43: FT25303430012344
A44: 24 | D44: 30/10/2025 11:07:53 | G44: 30/10/2025 | H44: 0 | I44: 1,400,000 | J44: 206,648,381 | L44: DINH HA ANH | M44: Dinh Ha Anh SV12x6x3 thang 10 | R44: FT25303249088520
A45: 25 | D45: 30/10/2025 10:32:29 | G45: 30/10/2025 | H45: 0 | I45: 2,200,000 | J45: 205,248,381 | L45: NGUYEN THI THUY | M45: NGUYEN DAN THU SV12x5x11 thang 10 Ma giao dich Trace423008 Trace 42 3008 | R45: FT25303943908805
A46: 26 | D46: 30/10/2025 05:38:04 | G46: 30/10/2025 | H46: 0 | I46: 1,000,000 | J46: 203,048,381 | L46: TRAN THANH HUNG | M46: MBVCB.11507485097.298870.tran duc a nh nop tien hoc t10/2025.CT tu 001 1000507585 TRAN THANH HUNG toi 2588 666868 CONG TY TNHH TRI THUC SAO VI ET tai MB- Ma GD ACSP/ df298870 | R46: FT25303302379944
A47: 27 | D47: 30/10/2025 01:34:33 | G47: 30/10/2025 | H47: 0 | I47: 900,000 | J47: 202,048,381 | L47: NGUYEN HUYEN NGA | M47: Phan Ngoc Ha SV12x2x4 thang 10 Ma giao dich Trace451177 Trace 45117 | R47: FT25303574185251
A48: 28 | D48: 29/10/2025 22:31:32 | G48: 29/10/2025 | H48: 0 | I48: 1,500,000 | J48: 201,148,381 | L48: PHAM THI THUY HANG | M48: MBVCB.11506704851.761721.Phan Quoc Tri SV12x2x22 thang 10.CT tu 001100 3661439 PHAM THI THUY HANG toi 2588 666868 CONG TY TNHH TRI THUC SAO VI ET tai MB- Ma GD ACSP/ nv761721 | R48: FT25302036202464
A49: 29 | D49: 29/10/2025 19:35:07 | G49: 29/10/2025 | H49: 0 | I49: 900,000 | J49: 199,648,381 | L49: NGUYEN THI KIM DUNG | M49: Le Duc Anh SV12x1x3 thang 10 291025 19 35 06 414377 Ma giao dich Tr ace414377 Trace 414377 | R49: FT25302395191088
A50: 30 | D50: 29/10/2025 18:43:11 | G50: 29/10/2025 | H50: 0 | I50: 1,400,000 | J50: 198,748,381 | L50: VU THU NGA | M50: Thai Thanh Thu SV12x6x17 thang 10 | R50: FT25302510844003
A51: 31 | D51: 29/10/2025 18:25:06 | G51: 29/10/2025 | H51: 0 | I51: 800,000 | J51: 197,348,381 | L51: VND-TGTT-TRAN THI HAU | M51: Tran Minh Quang 12A6 Thang 10 FT2 5302638538700 Ma giao dich Trace 610886 Trace 610886 | R51: FT25302567440772
A52: 32 | D52: 29/10/2025 17:39:35 | G52: 29/10/2025 | H52: 0 | I52: 1,800,000 | J52: 196,548,381 | L52: TRAN THI THANH HOA | M52: NGUYEN GIA NAM SV12X2X9 THANG 10- M a GD ACSP/ fz595972 | R52: FT25302023061045
A53: 33 | D53: 29/10/2025 17:39:18 | G53: 29/10/2025 | H53: 0 | I53: 1,700,000 | J53: 194,748,381 | L53: DONG THI NHUNG | M53: Dong Thi Nhung SV12x5x25 thang 10 | R53: FT25302224972728
A54: 34 | D54: 29/10/2025 11:04:27 | G54: 29/10/2025 | H54: 0 | I54: 2,200,000 | J54: 193,048,381 | L54: VND-TGTT-DO THI HAI YEN | M54: Pham Anh Vu SV12x5x13 thang 10 FT25 302790756070 Ma giao dich Trace9 61046 Trace 961046 | R54: FT25302047179677
A55: 35 | D55: 28/10/2025 22:14:47 | G55: 28/10/2025 | H55: 0 | I55: 1,800,000 | J55: 190,848,381 | L55: SACOMBANK | M55: IBFT Ngo Quang Tung SV12x2x15 thang 10 Ma giao dich Trace932763 Tra ce 932763 | R55: FT25301829647047
A56: 36 | D56: 28/10/2025 21:14:03 | G56: 28/10/2025 | H56: 0 | I56: 900000 | J56: 189,048,381 | L56: VND-TGTT-HA LAN PHUONG | M56: Tranminhtri 12a1 FT25301070418208 Ma giao dich Trace846244 Trace 84 6244 | R56: FT25301531016440
A57: 37 | D57: 28/10/2025 21:12:38 | G57: 28/10/2025 | H57: 0 | I57: 2500000 | J57: 188,148,381 | L57: PHAM THI NGA | M57: Ta Thanh Van SV12x3x24 thang 10 | R57: FT25301036200259
A58: 38 | D58: 28/10/2025 21:00:41 | G58: 28/10/2025 | H58: 0 | I58: 900000 | J58: 185,648,381 | L58: LE THUY TRANG | M58: LE THUY TRANG 12A1 nop tien hoc tha ng 10 | R58: FT25301784198879
A59: 39 | D59: 28/10/2025 18:30:17 | G59: 28/10/2025 | H59: 0 | I59: 1300000 | J59: 184,748,381 | L59: NGUYEN THI LANH | M59: DUONG DINH LOI SV12X3X33 THANG 10- Ma GD ACSP/ eV766902 | R59: FT25301710270015
A60: 40 | D60: 28/10/2025 14:25:18 | G60: 28/10/2025 | H60: 0 | I60: 900000 | J60: 183,448,381 | L60: NGUYEN THI BICH PHUONG | M60: Than Tue Minh SV12x2x29 thang 10 | R60: FT25301370908047
A61: 41 | D61: 28/10/2025 10:04:07 | G61: 28/10/2025 | H61: 0 | I61: 1400000 | J61: 182,548,381 | L61: LE KIM TRINH | M61: Vu le bao chau sv12x6x5 thang 10 FT 25301805065643 Ma giao dich Trac e818901 Trace 818901 | R61: FT25301407237925
A62: 42 | D62: 28/10/2025 09:14:25 | G62: 28/10/2025 | H62: 0 | I62: 1400000 | J62: 181,148,381 | L62: LE HUY HAI | M62: LE DUC TRUNG SV12X6X21 THANG 10- Ma GD ACSP/ w7125280 | R62: FT25301011060862
A63: 43 | D63: 28/10/2025 06:48:02 | G63: 28/10/2025 | H63: 0 | I63: 2500000 | J63: 179,748,381 | L63: VND-TGTT-HOANG THI XUYEN | M63: Nguyen Hoang Ha An SV12x3x25 thang 10 FT25301216703890 Ma giao dich Trace876152 Trace 876152 | R63: FT25301341850807
A64: 44 | D64: 27/10/2025 20:45:15 | G64: 27/10/2025 | H64: 0 | I64: 2300000 | J64: 177,248,381 | L64: TRAN THI HONG THANH | M64: QR Nguyen Duc Phuong SV12x3x5 tha ng 10- Ma GD ACSP/ Ai633749 | R64: FT25300791430302
A65: 45 | D65: 27/10/2025 20:42:07 | G65: 27/10/2025 | H65: 0 | I65: 900000 | J65: 174,948,381 | L65: NGUYEN THI KIM CUC | M65: Nguyen Thanh Duong SV12x2x27 thang 10 | R65: FT25300103676310
A66: 46 | D66: 27/10/2025 19:11:29 | G66: 27/10/2025 | H66: 0 | I66: 900000 | J66: 174,048,381 | L66: NGUYEN VU MAI ANH | M66: Nguyen Vu Mai Anh SV12x1x4 thang 10 | R66: FT25300192169605
A67: 47 | D67: 27/10/2025 17:11:57 | G67: 27/10/2025 | H67: 0 | I67: 2500000 | J67: 173,148,381 | L67: NGUYEN THI DANG | M67: Le Huy Hai SV12x3x23 thang 10 Ma giao dich Trace309747 Trace 309747 | R67: FT25300029517316
... A80: 60 | D80: 26/10/2025 19:33:00 | G80: 27/10/2025 | H80: 0 | I80: 900000 | J80: 151,548,381 | L80: BUI BAO NGOC | M80: Bui Bao Ngoc SV12x1x23 thang 10 | R80: FT25300295250272
A81: 61 | D81: 26/10/2025 16:27:09 | G81: 27/10/2025 | H81: 0 | I81: 900000 | J81: 150,648,381 | L81: VU XUAN HOA | M81: VU XUAN HOA chuyen tien | R81: FT25300710274403 | U81: Vũ Xuân Hải Đăng | V81: SV12x2x33
A82: 62 | D82: 25/10/2025 20:39:27 | G82: 25/10/2025 | H82: 0 | I82: 1700000 | J82: 149,748,381 | L82: VND-TGTT-PHUNG THI HUONG | M82: Nguyen hanh nguyen sv 12a5 thang 10 FT25300124910020 Ma giao dich T race531578 Trace 531578 | R82: FT25298999393228
A83: 63 | D83: 25/10/2025 19:53:45 | G83: 25/10/2025 | H83: 0 | I83: 900000 | J83: 148,048,381 | L83: VND-TGTT-NGO THI THUY MAY | M83: Tran Nguyen Vu SV 12a3 T10 FT252987 67397052 Ma giao dich Trace26745 7 Trace 267457 | R83: FT25298973048400
A84: 64 | D84: 25/10/2025 19:45:41 | G84: 25/10/2025 | H84: 0 | I84: 900000 | J84: 147,148,381 | L84: NGUYEN PHUONG THANH | M84: QR Hoang Hai Yen SV12x1x29 thang 10- Ma GD ACSP/ Qb559553 | R84: FT25298974969644
A85: 65 | D85: 25/10/2025 16:24:10 | G85: 25/10/2025 | H85: 0 | I85: 1400000 | J85: 146,248,381 | L85: HOANG THI ANH | M85: MB 2588666868 Nguyen Trung Kien SV1 2x5x7 thang 10- Ma GD ACSP/ R501913 1 | R85: FT25298691127983
A86: 66 | D86: 25/10/2025 13:22:56 | G86: 25/10/2025 | H86: 0 | I86: 800000 | J86: 144,848,381 | L86: NGUYEN THI PHUONG | M86: MBVCB.11449478390.438793.Nguyen Duc Anh SV12x6x32 thang 10.CT tu 03410 00065204 NGUYEN THI PHUONG toi 2588 666868 CONG TY TNHH TRI THUC SAO VI ET tai MB- Ma GD ACSP/ hw438793 | R86: FT25298600263306
A87: 67 | D87: 25/10/2025 13:05:40 | G87: 25/10/2025 | H87: 0 | I87: 2200000 | J87: 144,048,381 | L87: VU THI MAY | M87: Bui Duc Minh SV12x5x18 thang 10 M a giao dich Trace173946 Trace 1739 46 | R87: FT25298492240326
A88: 68 | D88: 25/10/2025 12:34:24 | G88: 25/10/2025 | H88: 0 | I88: 2500000 | J88: 141,848,381 | L88: VND-TGTT-LE KIEN CUONG | M88: Le Anh Tuan SV12x3x20 thang 10 FT25 298244788657 Ma giao dich Trace5 98002 Trace 598002 | R88: FT25298002140083
A89: 69 | D89: 25/10/2025 12:11:10 | G89: 25/10/2025 | H89: 0 | I89: 1800000 | J89: 139,348,381 | L89: HOANG XUAN TRUONG | M89: MBVCB.11448643310.893178.Hoang Long Nhat SV12x1x13 thang 10.CT tu 0011 001160281 HOANG XUAN TRUONG toi 258 8666868 CONG TY TNHH TRI THUC SAO V IET tai MB- Ma GD ACSP/ ej893178 | R89: FT25298067262552
A90: 70 | D90: 25/10/2025 06:09:25 | G90: 25/10/2025 | H90: 0 | I90: 2600000 | J90: 137,548,381 | L90: VND-TGTT-TAO NHU LAN | M90: Vu Hoang Viet SV12x3x36 thang 10 FT 25298050176611 Ma giao dich Trac e662715 Trace 662715 | R90: FT25298228401535
A91: 71 | D91: 24/10/2025 23:30:46 | G91: 25/10/2025 | H91: 0 | I91: 800000 | J91: 134,948,381 | L91: NGUYEN THI NGAN | M91: MBVCB.11444091117.783744.Vu Ngan Th uong SV12x3x11 thang 10.CT tu 10237 40729 NGUYEN THI NGAN toi 258866686 8 VSK CO. LTD tai MB- Ma GD ACSP/ r t783744 | R91: FT25298886299276
A92: 72 | D92: 24/10/2025 23:08:59 | G92: 25/10/2025 | H92: 0 | I92: 1800000 | J92: 134,148,381 | L92: NGUYEN THI PHUONG | M92: Nguyen Quang Thang SV12x2x14 thang 10 | R92: FT25298042108983
A93: 73 | D93: 24/10/2025 21:28:11 | G93: 24/10/2025 | H93: 0 | I93: 1800000 | J93: 132,348,381 | L93: TRAN THI DUYEN | M93: Vu Mai Phuong SV12x2x16 thang 10 Ma giao dich Trace630503 Trace 630 503 | R93: FT25297368437495
... A159: 139 | D159: 20/10/2025 16:28:08 | G159: 20/10/2025 | H159: 0 | I159: 900000 | J159: 44,684,006 | L159: MAU NGOC SON | M159: Mau Anh Vu SV12x3x38 thang 10 Ma giao dich Trace076333 Trace 076333 | R159: FT25293048526009
G160: TỔNG TIỀN | H160: 42,606,585 | I160: =SUM(I56:I159) -> 152700000
A161: Số dư cuối kỳ/ Closing Balance: 108,948,381 VND (Bằng chữ/ In Words:Một trăm lẻ tám triệu chín trăm bốn mươi tám nghìn ba trăm tám mươi mốt VND )
A162: Chứng từ này được xuất tự động từ hệ thống của Ngân hàng TMCP Quân đội./ This document is automatically exported from MBBank's System

Sheet TH
B1: Signature Not Verified Da ky boi Ngan hang TMCP Quan doi. Ngay ky : Wed Oct 22 12:53:26 ICT 2025 SỔ PHỤ CHI TIẾT KIÊM BÁO NỢ/BÁO CÓ NGÂN HÀNG TMCP QUÂN ĐỘI Account Statement/Debit/Credit transaction Military Commercial Joint Stock Bank
B2: Số tài khoản/Account No: 0670190997777 Tên tài khoản/Account name: NGUYEN THI HUYEN Loại tiền/Currency: VND Kỳ sao kê/Statement period: Từ ngày/From: 10/10/2025 Đến ngày/To: 22/10/2025
B3: Chúng tôi xin thông báo chi tiết phát sinh nợ/có trên tài khoản quý khách trong thời gian trên như sau: We would like to inform you about your account debit/credit transactions as the following details:
A6: ATT | B6: Ngày giao dịch Transaction Date | C6: Số bút toán Transaction No | D6: Phát sinh nợ Debit | E6: Phát sinh có Credit | F6: Nội dung Details | G6: Đơn vị thụ hưởng/Đơn vị chuyển Beneficiary/Applicant | H6: Tài khoản Account | I6: Ngân hàng đối tác Remitter Bank
B7: 07/11/2025 08:36 | C7: FT25311646938538 | D7: 0 | E7: 900000 | F7: LUONG THI THU TRANG QR Nguyen Minh Anh SV10x1x1 thang 10- Ma GD ACSP/ A9433002 | G7: NGUYEN THI HUYEN | H7: 670190997777 | I7: MB
B8: 06/11/2025 20:26 | C8: FT25310850357981 | D8: 0 | E8: 800000 | F8: CUSTOMER Nguyen Ha Vy SV12x9x9 thang 10 0611 25 20 26 47 014646 Ma giao dich Trace014646 Trace 014646 | G8: NGUYEN THI HUYEN | H8: 670190997777 | I8: MB
B9: 06/11/2025 18:44 | C9: FT25310212719476 | D9: 0 | E9: 800000 | F9: LE THI ANH QR Dao Quynh Huong SV10x5x4 thang 10- Ma GD ACSP/ jv220875 | G9: NGUYEN THI HUYEN | H9: 670190997777 | I9: MB
B10: 06/11/2025 12:17 | C10: FT25310091500601 | D10: 0 | E10: 500000 | F10: CHU THI HOA MBVCB.11606150212.502622.Mai Truong Giang SV10x14x2 thang 10.CT tu 054 1000177955 CHU THI HOA toi 06701909 97777 NGUYEN THI HUYEN tai MB- Ma G | G10: NGUYEN THI HUYEN | H10: 670190997777 | I10: MB
B11: 06/11/2025 12:04 | C11: FT25310268801899 | D11: 0 | E11: 900000 | F11: CUSTOMER Tran Yen Nhi SV10x14x9 thang 10. TU: NGUYEN THI THU HUONG | G11: NGUYEN THI HUYEN | H11: 670190997777 | I11: MB
B12: 06/11/2025 11:18 | C12: FT25310745533139 | D12: 0 | E12: 500000 | F12: HOANG THI LIEN QR Nguyen Hoang Ngan SV10x14x7 th ang 10- Ma GD ACSP/ 8k591211 | G12: NGUYEN THI HUYEN | H12: 670190997777 | I12: MB
B13: 05/11/2025 23:33 | C13: FT25310192656078 | D13: 0 | E13: 700000 | F13: DAO THE TUAN MBVCB.11600665858.103329.Dao Thi Ma i Anh N.V.Cu SV 10.3.51 chuyen ti en.CT tu 1029662853 DAO THE TUAN to i 0670190997777 NGUYEN THI HUYEN ta | G13: NGUYEN THI HUYEN | H13: 670190997777 | I13: MB
B14: 05/11/2025 19:08 | C14: FT25309210450052 | D14: 0 | E14: 1300000 | F14: CUSTOMER Bui Phuong Thao SV10x14x13 thang 10. TU: BUI VAN TUONG | G14: NGUYEN THI HUYEN | H14: 670190997777 | I14: MB
B15: 05/11/2025 17:23 | C15: FT25309036004965 | D15: 0 | E15: 800000 | F15: CUSTOMER Dinh Nguyen Duong SV11x1x16 thang 1 0 FT25309027080130 Ma giao dich Trace638874 Trace 638874 | G15: NGUYEN THI HUYEN | H15: 670190997777 | I15: MB
B16: 05/11/2025 16:47 | C16: FT25309150131183 | D16: 0 | E16: 900000 | F16: VU PHUONG NAM VU NGUYEN KHANH AN SV10X12X2 THANG 10- Ma GD ACSP/ gD746328 | G16: NGUYEN THI HUYEN | H16: 670190997777 | I16: MB
B17: 05/11/2025 15:40 | C17: FT25309797540820 | D17: 0 | E17: 600000 | F17: TRAN THANH LOAN QR Tran Nhat Nam SV12x7x4 thang 1 0- Ma GD ACSP/ Cj834731 | G17: NGUYEN THI HUYEN | H17: 670190997777 | I17: MB
A18: 1 | B18: 05/11/2025 08:29 | C18: FT25309266316630 | D18: 0 | E18: 500000 | F18: LE THI HIEN QR Pham Thu Huong SV10x7x9 thang 10- Ma GD ACSP/ 3K476369 | G18: NGUYEN THI HUYEN | H18: 670190997777 | I18: MB
A19: 2 | B19: 05/11/2025 08:24 | C19: FT25309160722352 | D19: 0 | E19: 800000 | F19: PHAM THI KIM HOA MBVCB.11587030617.845416.Do Tuan Mi nh SV12x9x11 thang 10.CT tu 1017167 332 PHAM THI KIM HOA toi 0670190997 777 NGUYEN THI HUYEN tai MB- Ma GD | G19: NGUYEN THI HUYEN | H19: 670190997777 | I19: MB
A20: 3 | B20: 05/11/2025 08:17 | C20: FT25309140205867 | D20: 0 | E20: 400000 | F20: NGUYEN THI THU HUYEN MBVCB.11586955396.791050. Nguyen Phu ong Anh SV10x14x20 thang 10.CT tu 1 023105610 NGUYEN THI THU HUYEN toi 0670190997777 NGUYEN THI HUYEN tai | G20: NGUYEN THI HUYEN | H20: 670190997777 | I20: MB
A21: 4 | B21: 05/11/2025 06:07 | C21: FT25309040656982 | D21: 0 | E21: 800000 | F21: VU HUYEN HANH MBVCB.11585692740.990790.Do Vu Ba L inh SV11x4x1 thang 10.CT tu 0011001 386041 VU HUYEN HANH toi 0670190997 777 NGUYEN THI HUYEN tai MB- Ma GD | G21: NGUYEN THI HUYEN | H21: 670190997777 | I21: MB
A22: 5 | B22: 04/11/2025 23:42 | C22: FT25309890073971 | D22: 0 | E22: 800000 | F22: CUSTOMER Pham Hoang Minh SV11x7x3 thang 10 F T25309007223058 Ma giao dich Tra ce387703 Trace 387703 | G22: NGUYEN THI HUYEN | H22: 670190997777 | I22: MB
A23: 6 | B23: 04/11/2025 22:46 | C23: FT25309878431400 | D23: 0 | E23: 2400000 | F23: CUSTOMER PHAN THI MINH NGUYET chuyen Nguyen Bao Viet SV12x4x6 thang 10 FT253093 10140091 Ma giao dich Trace25663 8 Trace 256638 | G23: NGUYEN THI HUYEN | H23: 670190997777 | I23: MB
A24: 7 | B24: 04/11/2025 22:42 | C24: FT25309350952559 | D24: 0 | E24: 1100000 | F24: CUSTOMER Nguyen Van Tuan SV12x8x13 thang 10 FT25309146345065 Ma giao dich Tr ace246151 Trace 246151 | G24: NGUYEN THI HUYEN | H24: 670190997777 | I24: MB
A25: 8 | B25: 04/11/2025 22:22 | C25: FT25309220426209 | D25: 0 | E25: 500000 | F25: ZION ZALOPAY-CHUYENTIEN-O5CH7BMCK1PB-Din h Minh Dang SV12x7x6 thang 10. TU: ZION | G25: NGUYEN THI HUYEN | H25: 670190997777 | I25: MB
A26: 9 | B26: 04/11/2025 22:13 | C26: FT25309480081186 | D26: 0 | E26: 600000 | F26: NGUYEN VIET HAI NGUYEN VIET HAI Chuyen tien em Duc Anh mon Anh- Ma GD ACSP/ Y3848274 | G26: NGUYEN THI HUYEN | H26: 670190997777 | I26: MB | J26: Nguyễn Việt Đức Anh | K26: SV12x7x1
A27: 10 | B27: 04/11/2025 21:59 | C27: FT25308700570767 | D27: 0 | E27: 700000 | F27: DUONG THI THU HANG HOANG THU THUY NVC SV11. 3.42 DONG T IEN THANG 10- Ma GD ACSP/ RD174356 | G27: NGUYEN THI HUYEN | H27: 670190997777 | I27: MB
A28: 11 | B28: 04/11/2025 21:55 | C28: FT25308728272670 | D28: 0 | E28: 300000 | F28: CUSTOMER HOANG THI SUONG chuyen tien. TU: HOANG THI SUONG | G28: NGUYEN THI HUYEN | H28: 670190997777 | I28: MB | J28: Ngỗ Hải Anh | K28: 11A11
A29: 12 | B29: 04/11/2025 21:39 | C29: FT25308878760240 | D29: 0 | E29: 800000 | F29: CUSTOMER Quach Ngoc Tuan SV12x8x18 thang 10 Ma giao dich Trace419972 Trace 4 19972 | G29: NGUYEN THI HUYEN | H29: 670190997777 | I29: MB
A30: 13 | B30: 04/11/2025 21:00 | C30: FT25308047834781 | D30: 0 | E30: 1000000 | F30: NGUYEN THI HIEN NGUYEN HOANG NAM SV11X1X2 THANG 10- Ma GD ACSP/ pB853950 | G30: NGUYEN THI HUYEN | H30: 670190997777 | I30: MB
A31: 14 | B31: 04/11/2025 20:53 | C31: FT25308542788499 | D31: 0 | E31: 800000 | F31: LE THI LAN QR Nguyen Ngoc Bao Tram SV12x9x9 thang 10- Ma GD ACSP/ rV654894 | G31: NGUYEN THI HUYEN | H31: 670190997777 | I31: MB
A32: 15 | B32: 04/11/2025 20:46 | C32: FT25308680911398 | D32: 0 | E32: 400000 | F32: ZION ZALOPAY-CHUYENTIEN-O5CH7BMCHOSC-Tra n Duc Anh SV10x8x2 thang 10. TU: ZION | G32: NGUYEN THI HUYEN | H32: 670190997777 | I32: MB
A33: 16 | B33: 04/11/2025 20:16 | C33: FT25308567996616 | D33: 0 | E33: 800000 | F33: CUSTOMER Nguyen Quoc Hung SV12x4x19 thang 10 FT25308800049097 Ma giao dich T race535794 Trace 535794 | G33: NGUYEN THI HUYEN | H33: 670190997777 | I33: MB
A34: 17 | B34: 04/11/2025 19:59 | C34: FT25308546259469 | D34: 0 | E34: 800000 | F34: CUSTOMER Bui Duc Nhat Minh SV10x5x5 thang 10 FT25308214308386 Ma giao dich T race432833 Trace 432833 | G34: NGUYEN THI HUYEN | H34: 670190997777 | I34: MB
A35: 18 | B35: 04/11/2025 19:34 | C35: FT25308070363014 | D35: 0 | E35: 700000 | F35: CUSTOMER con Dinh Vu Ha Anh nop tien t10. TU: VU THI HA | G35: NGUYEN THI HUYEN | H35: 670190997777 | I35: MB
A36: 19 | B36: 04/11/2025 19:17 | C36: FT25308844392209 | D36: 0 | E36: 1200000 | F36: QUAN THUY DUONG QR Trinh Ngoc Nguyen Khang SV12x1 6x20 thang 10- Ma GD ACSP/ L1319560 | G36: NGUYEN THI HUYEN | H36: 670190997777 | I36: MB
A37: 20 | B37: 04/11/2025 19:08 | C37: FT25308862069941 | D37: 0 | E37: 900000 | F37: CUSTOMER Luu Tra My SV12x11x29 thang 10 FT25 308295030794 Ma giao dich Trace0 85600 Trace 085600 | G37: NGUYEN THI HUYEN | H37: 670190997777 | I37: MB
A38: 21 | B38: 04/11/2025 19:06 | C38: FT25308429538416 | D38: 0 | E38: 300000 | F38: DO THANH TRUNG MB 0670190997777 Do Tuan Anh SV11x8 x15 thang 10- Ma GD ACSP/ 8I073308 | G38: NGUYEN THI HUYEN | H38: 670190997777 | I38: MB
A39: 22 | B39: 04/11/2025 19:03 | C39: FT25308384080295 | D39: 0 | E39: 900000 | F39: CUSTOMER Ngo Gia Bao Nhi SV11x6x28 thang 10 Ma giao dich Trace925085 Trace 9 25085 | G39: NGUYEN THI HUYEN | H39: 670190997777 | I39: MB
A40: 23 | B40: 04/11/2025 18:34 | C40: FT25308931040379 | D40: 0 | E40: 600000 | F40: CUSTOMER Truong Ba Bao Nam SV11x8x12 thang 1 0. TU: TRAN THI THU THUAN | G40: NGUYEN THI HUYEN | H40: 670190997777 | I40: MB
... A73: 56 | B73: 03/11/2025 19:36 | C73: FT25307836767802 | D73: 0 | E73: 300000 | F73: NGUYEN THI VAN ANH NGUYEN KHANH LINH SV11X11X8 THANG 1 0- Ma GD ACSP/ gK953313 | G73: NGUYEN THI HUYEN | H73: 670190997777 | I73: MB
A74: 57 | B74: 03/11/2025 19:05 | C74: FT25307502224197 | D74: 0 | E74: 1157000 | F74: CUSTOMER con Ngo Kim Ngan 10a2 nop. TU: NGUYEN THI DUONG | G74: NGUYEN THI HUYEN | H74: 670190997777 | I74: MB | J74: dư 1,157k
A75: 58 | B75: 03/11/2025 18:31 | C75: FT25307719113228 | D75: 0 | E75: 1400000 | F75: CUSTOMER Dao Ha An SV11x6x2 thang 10. TU: NGUYEN THU HUYEN | G75: NGUYEN THI HUYEN | H75: 670190997777 | I75: MB
A76: 59 | B76: 03/11/2025 13:04 | C76: FT25307851004091 | D76: 0 | E76: 600000 | F76: NGUYEN THI THUY kKieu msnh Dung sv10x5x14 nop tien thang 10- Ma GD ACSP/ KH392015 | G76: NGUYEN THI HUYEN | H76: 670190997777 | I76: MB
A77: 60 | B77: 03/11/2025 09:18 | C77: FT25307589005742 | D77: 0 | E77: 600000 | F77: MB Tran Ngoc Bao Tram SV11x8x9 thang 1 0 | G77: NGUYEN THI HUYEN | H77: 670190997777 | I77: MB
A78: 61 | B78: 02/11/2025 21:05 | C78: FT25307011910109 | D78: 0 | E78: 900000 | F78: NGUYEN THI THANH THUY MBVCB. 11556921195.258908.Nguyen Ha Phuong SV11x6x30 thang 10. CT tu 001 1000567257 NGUYEN THI THANH THUY to i 0670190997777 NGUYEN THI HUYEN ta | G78: NGUYEN THI HUYEN | H78: 670190997777 | I78: MB
A79: 62 | B79: 02/11/2025 17:10 | C79: FT25307880017032 | D79: 0 | E79: 800000 | F79: NGUYEN THI KIM BICH MBVCB.11553449520.987977.tran namkh anh sv12.4.19.CT tu 0011000604595 N GUYEN THI KIM BICH toi 067019099777 7 NGUYEN THI HUYEN tai MB- Ma GD AC | G79: NGUYEN THI HUYEN | H79: 670190997777 | I79: MB
A80: 63 | B80: 01/11/2025 23:28 | C80: FT25307833616971 | D80: 0 | E80: 200000 | F80: CUSTOMER Dam Yen Nhi SV10x6x3 thang 10 Ma giao dich Trace840754 Trace 840754 | G80: NGUYEN THI HUYEN | H80: 670190997777 | I80: MB
A81: 64 | B81: 01/11/2025 22:51 | C81: FT25307808554781 | D81: 0 | E81: 1100000 | F81: DANG TIEN LUC DANG THE QUANG SV10X14X16 THANG 10- Ma GD ACSP/ x8400455 | G81: NGUYEN THI HUYEN | H81: 670190997777 | I81: MB
A82: 65 | B82: 01/11/2025 22:35 | C82: FT25307292384017 | D82: 0 | E82: 2500000 | F82: NGUYEN THI HAI LE NGUYEN BA HAI BANG SV11X3X2 THANG 1 0- Ma GD ACSP/ vS354249 | G82: NGUYEN THI HUYEN | H82: 670190997777 | I82: MB
A83: 66 | B83: 01/11/2025 21:44 | C83: FT25305784173410 | D83: 0 | E83: 400000 | F83: CUSTOMER Tong Gia Han SV10x8x23 thang 10 FT2 5307010345007 Ma giao dich Trace 092976 Trace 092976 | G83: NGUYEN THI HUYEN | H83: 670190997777 | I83: MB
A84: 67 | B84: 01/11/2025 21:27 | C84: FT25305456604078 | D84: 0 | E84: 300000 | F84: NGO THI TAN THANH con Minh Huong 11A11 ck Van T10- Ma GD ACSP/ bv334537 | G84: NGUYEN THI HUYEN | H84: 670190997777 | I84: MB
A85: 68 | B85: 01/11/2025 21:21 | C85: FT25305399214324 | D85: 0 | E85: 1000000 | F85: VUONG THI HANG MBVCB.11544137355.662626.Ngo Ngoc A nh SV10x12x31 thang 10.CT tu 001100 0586008 VUONG THI HANG toi 06701909 97777 NGUYEN THI HUYEN tai MB- Ma G | G85: NGUYEN THI HUYEN | H85: 670190997777 | I85: MB
A86: 69 | B86: 01/11/2025 17:39 | C86: FT25305360769308 | D86: 0 | E86: 300000 | F86: LE THU TRANG MBVCB.11541025172.612688.Ngo Dinh Q uoc Thai SV11x11x4 thang 10.CT tu 1 047604643 LE THU TRANG toi 06701909 97777 NGUYEN THI HUYEN tai MB- Ma G | G86: NGUYEN THI HUYEN | H86: 670190997777 | I86: MB
... A108: 91 | B108: 31/10/2025 21:49 | C108: FT25304710947932 | D108: 0 | E108: 400000 | F108: CUSTOMER Tran Hai Anh SV11x6x4 thang 10 mon li.. TU: NGUYEN THI KIM OANH | G108: NGUYEN THI HUYEN | H108: 670190997777 | I108: MB
A109: 92 | B109: 31/10/2025 21:26 | C109: FT25304570054985 | D109: 0 | E109: 300000 | F109: NGUYEN THI UYEN CON TUAN VU NOP TIEN HOC BO TRO THA NG10 CO NHE- Ma GD ACSP/ KY956040 | G109: NGUYEN THI HUYEN | H109: 670190997777 | I109: MB | J109: SV10x9x14
A110: 93 | B110: 31/10/2025 21:11 | C110: FT25304810009173 | D110: 0 | E110: 700000 | F110: CUSTOMER Nguyen Minh Anh SV12x16x1 thang 10 Ma giao dich Trace236249 Trace 2 36249 | G110: NGUYEN THI HUYEN | H110: 670190997777 | I110: MB
A111: 94 | B111: 31/10/2025 20:41 | C111: FT25304603601803 | D111: 0 | E111: 500000 | F111: PHAN THI CHUC MBVCB.11530848296.776351.Nguyen Thi Minh Thu SV10x16x18 thang 10.CT tu 0541000249215 PHAN THI CHUC toi 06 70190997777 NGUYEN THI HUYEN tai MB | G111: NGUYEN THI HUYEN | H111: 670190997777 | I111: MB | J111: dư 500k
A112: 95 | B112: 31/10/2025 20:31 | C112: FT25304701470570 | D112: 0 | E112: 400000 | F112: CUSTOMER NGUYEN THU THUY CHUYEN TIEN tien ho c cua em Nam Khanh a Ma giao dich Trace283573 Trace 283573 | G112: NGUYEN THI HUYEN | H112: 670190997777 | I112: MB
A113: 96 | B113: 31/10/2025 20:27 | C113: FT25304027379463 | D113: 0 | E113: 1800000 | F113: BUI HONG QUAN BUI HONG QUAN CHUYEN TIEN CON BUI Q UANG HUY 12A 2 SV.1.2.2.1 THANG 10- Ma GD ACSP/ Yv603585 | G113: NGUYEN THI HUYEN | H113: 670190997777 | I113: MB
A114: 97 | B114: 31/10/2025 20:12 | C114: FT25304909304502 | D114: 0 | E114: 1700000 | F114: TRAN DUC QUAN TRAN DUC ANH SV11X3X21 THANG 10- Ma GD ACSP/ 6l496886 | G114: NGUYEN THI HUYEN | H114: 670190997777 | I114: MB
A115: 98 | B115: 31/10/2025 19:50 | C115: FT25304368105270 | D115: 0 | E115: 2500000 | F115: PHAM THI NGUYET QADHEX8475 APPMB1 1 hs Nguyen Min h Duc lop 12A1 dong tien thang 10. TU: PHAM THI NGUYET | G115: NGUYEN THI HUYEN | H115: 670190997777 | I115: MB
A116: 99 | B116: 31/10/2025 19:47 | C116: FT25304008618616 | D116: 0 | E116: 900000 | F116: CUSTOMER Tran Hai Anh SV lop 11A7 dong t hoc toan.. TU: NGUYEN THI KIM OANH | G116: NGUYEN THI HUYEN | H116: 670190997777 | I116: MB | J116: sv11x6x4
A117: 100 | B117: 31/10/2025 19:08 | C117: FT25304000778190 | D117: 0 | E117: 3100000 | F117: CUSTOMER Pham Gia Khanh SV12.3.8. TU: NGUYEN THI MINH PHUONG | G117: NGUYEN THI HUYEN | H117: 670190997777 | I117: MB
A118: 101 | B118: 31/10/2025 18:47 | C118: FT25304305343068 | D118: 0 | E118: 800000 | F118: CUSTOMER Ng Tran Bao Linh SV12x12x11 thang 1 0. TU: TRAN THI BINH TRAN THI BINH | G118: NGUYEN THI HUYEN | H118: 670190997777 | I118: MB
A119: 102 | B119: 31/10/2025 18:04 | C119: FT25304239830612 | D119: 0 | E119: 900000 | F119: CUSTOMER Le Nguyen Hong Anh 11A6 FT253046205 03467 Ma giao dich Trace861349 T race 861349 | G119: NGUYEN THI HUYEN | H119: 670190997777 | I119: MB | J119: SV11x6x33
A120: 103 | B120: 31/10/2025 15:43 | C120: FT25304925486370 | D120: 0 | E120: 500000 | F120: HOANG THE NGUYEN HOANG THE NGUYEN CHUYEN TIEN EM HOA NG MINH PHUONG DONG TIEN HOC THEM T OAN- Ma GD ACSP/ Wj417852 | G120: NGUYEN THI HUYEN | H120: 670190997777 | I120: MB | J120: SV10x7x16
A121: 104 | B121: 31/10/2025 15:41 | C121: FT25304390216460 | D121: 0 | E121: 600000 | F121: CUSTOMER Mai Khanh Huyen SV11x4x5 thang 10. TU: NGUYEN THI LINH | G121: NGUYEN THI HUYEN | H121: 670190997777 | I121: MB
A122: 105 | B122: 31/10/2025 15:40 | C122: FT25304300883774 | D122: 0 | E122: 1300000 | F122: DAO PHUONG MAI MBVCB.11526190671.697044.HS Truong Duc Gia Bao 10 A5nop tien hoc T10.C T tu 1029657448 DAO PHUONG MAI toi 0670190997777 NGUYEN THI HUYEN tai | G122: NGUYEN THI HUYEN | H122: 670190997777 | I122: MB
A123: 106 | B123: 31/10/2025 13:09 | C123: FT25304081095991 | D123: 0 | E123: 300000 | F123: TRAN THI THANH HUYEN TRAN THI THANH HUYEN CHUYEN TIEN- M a GD ACSP/ lc545994 | G123: NGUYEN THI HUYEN | H123: 670190997777 | I123: MB | J123: Nguyễn Minh Sơn | K123: SV10x9x10
A124: 107 | B124: 31/10/2025 12:45 | C124: FT25304537657850 | D124: 0 | E124: 800000 | F124: CUSTOMER Pham Gia Minh SV11x1x20 thang 10 Ma giao dich Trace351369 Trace 351 369 | G124: NGUYEN THI HUYEN | H124: 670190997777 | I124: MB
A125: 108 | B125: 31/10/2025 12:22 | C125: FT25304210091553 | D125: 0 | E125: 300000 | F125: CUSTOMER 10A9 Duong Nguyen Phuong Linh chuye n tien FT25304845842355 Ma giao d ich Trace761412 Trace 761412 | G125: NGUYEN THI HUYEN | H125: 670190997777 | I125: MB
A126: 109 | B126: 31/10/2025 12:01 | C126: FT25304840581700 | D126: 0 | E126: 300000 | F126: CUSTOMER Nguyen Quang Son dong hoc toan than g 10 FT25304079565001 Ma giao dic h Trace627851 Trace 627851 | G126: NGUYEN THI HUYEN | H126: 670190997777 | I126: MB | J126: SV10x9x11
A127: 110 | B127: 31/10/2025 11:56 | C127: FT25304474060808 | D127: 0 | E127: 500000 | F127: NGUYEN THANH LONG QR Nguyen Trung Hieu SV10x16x9 th ang 10- Ma GD ACSP/ 3V922630 | G127: NGUYEN THI HUYEN | H127: 670190997777 | I127: MB | J127: Dư lần 2 500k
A128: 111 | B128: 31/10/2025 11:48 | C128: FT25304083891100 | D128: 0 | E128: 500000 | F128: VU THI THU TRANG DOAN NAM PHONG SV10X16X18 THANG 10- Ma GD ACSP/ dc069045 | G128: NGUYEN THI HUYEN | H128: 670190997777 | I128: MB | J128: SV10x16x15
A129: 112 | B129: 31/10/2025 11:37 | C129: FT25304701043057 | D129: 0 | E129: 300000 | F129: CUSTOMER Nguyen Bao Chau SV10x9x1 thang 10 Ma giao dich Trace319099 Trace 31 9099 | G129: NGUYEN THI HUYEN | H129: 670190997777 | I129: MB
A130: 113 | B130: 31/10/2025 11:32 | C130: FT25304372710770 | D130: 0 | E130: 600000 | F130: CUSTOMER Pham The Anh SV 10x17x1 Tieng anh T 10. TU: PHAM VAN ANH | G130: NGUYEN THI HUYEN | H130: 670190997777 | I130: MB
A131: 114 | B131: 31/10/2025 11:22 | C131: FT25304708052859 | D131: 0 | E131: 500000 | F131: CUSTOMER Pham Le Thu Minh SV10x7x14 thang 10 FT25304833053207 Ma giao dich T race384908 Trace 384908 | G131: NGUYEN THI HUYEN | H131: 670190997777 | I131: MB
A132: 115 | B132: 31/10/2025 11:17 | C132: FT25304398215724 | D132: 0 | E132: 400000 | F132: DUONG THI LANG MBVCB.11523003140.631427.DUONG THI LANG chuyen tien.CT tu 2981321788 D UONG THI LANG toi 0670190997777 NGU YEN THI HUYEN tai MB- Ma GD ACSP/ v | G132: NGUYEN THI HUYEN | H132: 670190997777 | I132: MB
A133: 116 | B133: 31/10/2025 11:14 | C133: FT25304260224902 | D133: 0 | E133: 300000 | F133: CUSTOMER IBFT con Doan Thuy Bich lop 10A16 n op tien hoc toan TT Ma giao dich Trace029880 Trace 029880 | G133: NGUYEN THI HUYEN | H133: 670190997777 | I133: MB
A134: 117 | B134: 31/10/2025 11:13 | C134: FT25304836340440 | D134: 0 | E134: 1900000 | F134: CUSTOMER Hs Bui Phuc Hung lop 10a12 nop tien hoc . TU: BUI QUANG VAN | G134: NGUYEN THI HUYEN | H134: 670190997777 | I134: MB
A135: 118 | B135: 31/10/2025 11:13 | C135: FT25304091396502 | D135: 0 | E135: 700000 | F135: CUSTOMER TRINH HA VY SV10x2x14 FT25304149008 236 Ma giao dich Trace325364 Tra ce 325364 | G135: NGUYEN THI HUYEN | H135: 670190997777 | I135: MB
A136: 119 | B136: 31/10/2025 11:06 | C136: FT25304886272980 | D136: 0 | E136: 300000 | F136: CUSTOMER Hoang Thanh Phong SV10x10x10 thang 10. TU: TRAN THI THU | G136: NGUYEN THI HUYEN | H136: 670190997777 | I136: MB
A137: 120 | B137: 31/10/2025 10:53 | C137: FT25304410010058 | D137: 0 | E137: 600000 | F137: BUI DUC DAI CON HAI MINH 10A10 DONG TIEN HOC TO AN- Ma GD ACSP/ wo686158 | G137: NGUYEN THI HUYEN | H137: 670190997777 | I137: MB
A138: 121 | B138: 31/10/2025 10:46 | C138: FT25304780803145 | D138: 0 | E138: 500000 | F138: CUSTOMER Nguyen Trung Hieu SV10x16x9 thang 1 0 FT25304065808105 Ma giao dich Trace171273 Trace 171273 | G138: NGUYEN THI HUYEN | H138: 670190997777 | I138: MB
A139: 122 | B139: 31/10/2025 10:17 | C139: FT25304301883414 | D139: 0 | E139: 600000 | F139: TRAN THI QUYNH MAI QR Do Anh Thu SV10x10x17 thang 10 - Ma GD ACSP/ j2607964 | G139: NGUYEN THI HUYEN | H139: 670190997777 | I139: MB | J139: Đặng Anh Thư SV10x10x15
A140: 123 | B140: 31/10/2025 09:51 | C140: FT25304264764875 | D140: 0 | E140: 600000 | F140: NGO THI THAO DO THI QUE PHUONG SV10X12X13 THANG 10- Ma GD ACSP/ ic296482 | G140: NGUYEN THI HUYEN | H140: 670190997777 | I140: MB
A141: 124 | B141: 31/10/2025 08:52 | C141: FT25304379592990 | D141: 0 | E141: 800000 | F141: CUSTOMER le hoang long lop12a12 nopthang 10. TU: LUONG THI NGUYET | G141: NGUYEN THI HUYEN | H141: 670190997777 | I141: MB
A142: 125 | B142: 31/10/2025 07:14 | C142: FT25304840247988 | D142: 0 | E142: 900000 | F142: CUSTOMER Pham Hien Long SV11x2x19 thang 10. TU: PHAM XUAN THANH | G142: NGUYEN THI HUYEN | H142: 670190997777 | I142: MB
A143: 126 | B143: 31/10/2025 07:12 | C143: FT25304947223707 | D143: 0 | E143: 200000 | F143: DOAN MINH DUC QR Pham Nam Khanh SV10x9x7 thang 10- Ma GD ACSP/ Dj135998 | G143: NGUYEN THI HUYEN | H143: 670190997777 | I143: MB
A144: 127 | B144: 31/10/2025 07:06 | C144: FT25304779325050 | D144: 0 | E144: 800000 | F144: CUSTOMER Ngo Gia Huy SV12x12x7 thang 10 Ma giao dich Trace299482 Trace 29948 | G144: NGUYEN THI HUYEN | H144: 670190997777 | I144: MB
A145: 128 | B145: 31/10/2025 06:34 | C145: FT25304490020210 | D145: 0 | E145: 900000 | F145: CUSTOMER Nguyen Thi Thanh Ngan SV12x16x13 th ang 10. TU: NGUYEN TUAN ANH | G145: NGUYEN THI HUYEN | H145: 670190997777 | I145: MB
A146: 129 | B146: 31/10/2025 05:55 | C146: FT25304675000696 | D146: 0 | E146: 500000 | F146: DANG VAN MINH MBVCB.11519827684.497105.Dang Minh Duc SV11x7x9 thang 10.CT tu 0011002 295447 DANG VAN MINH toi 0670190997 777 NGUYEN THI HUYEN tai MB- Ma GD | G146: NGUYEN THI HUYEN | H146: 670190997777 | I146: MB
A147: 130 | B147: 30/10/2025 22:44 | C147: FT25304583620784 | D147: 0 | E147: 900000 | F147: VU XUAN THANG MBVCB.11519074584.989600.Vu Ha Anh SV10x16x4 thang 10.CT tu 0611001553 344 VU XUAN THANG toi 0670190997777 NGUYEN THI HUYEN tai MB- Ma GD ACS | G147: NGUYEN THI HUYEN | H147: 670190997777 | I147: MB
A148: 131 | B148: 30/10/2025 22:28 | C148: FT25304455710063 | D148: 0 | E148: 900000 | F148: TRAN THI HOA MAI MBVCB.11518976873.924413.Nguyen Yen Nhi SV12x16x15 thang 10.CT tu 0011 000517147 TRAN THI HOA MAI toi 0670 190997777 NGUYEN THI HUYEN tai MB- | G148: NGUYEN THI HUYEN | H148: 670190997777 | I148: MB | J148: Dư 900k
A149: 132 | B149: 30/10/2025 22:08 | C149: FT25304590021483 | D149: 0 | E149: 1600000 | F149: CUSTOMER Hoang Tri Hien SV10x14x4 thang 10. TU: NGUYEN THI QUYNH THU | G149: NGUYEN THI HUYEN | H149: 670190997777 | I149: MB
A150: 133 | B150: 30/10/2025 21:54 | C150: FT25303673873456 | D150: 0 | E150: 600000 | F150: VU THI KIM THOA NGUYEN VU NGOC ANH SV11X8X3 THANG 1 0- Ma GD ACSP/ XQ645334 | G150: NGUYEN THI HUYEN | H150: 670190997777 | I150: MB
A151: 134 | B151: 30/10/2025 21:54 | C151: FT25303677629981 | D151: 0 | E151: 300000 | F151: CUSTOMER NGUYEN THI HOA chuyen tien HP cua c on Nguyen Thu Trang lop 12a7. TU: NGUYEN THI HOA | G151: NGUYEN THI HUYEN | H151: 670190997777 | I151: MB
A152: 135 | B152: 30/10/2025 21:49 | C152: FT25303703705078 | D152: 0 | E152: 800000 | F152: TRAN THI THEM MBVCB.11518680507.725571.Tran Minh Thai SV12x7x8 thang 10.CT tu 054100 0254784 TRAN THI THEM toi 067019099 7777 NGUYEN THI HUYEN tai MB- Ma GD | G152: NGUYEN THI HUYEN | H152: 670190997777 | I152: MB
A153: 136 | B153: 30/10/2025 21:43 | C153: FT25303078662594 | D153: 0 | E153: 900000 | F153: NGUYEN THI TRA GIANG MBVCB.11518620661.688890. Le Quang H uy SV12x10x1 thang 10.CT tu 0501000 097233 NGUYEN THI TRA GIANG toi 067 0190997777 NGUYEN THI HUYEN tai MB- | G153: NGUYEN THI HUYEN | H153: 670190997777 | I153: MB
A154: 137 | B154: 30/10/2025 21:35 | C154: FT25303916879972 | D154: 0 | E154: 600000 | F154: PHI THI VIET DUC MBVCB.11518558146.640975.Nguyen Nga n Anh SV10x17x13 thang 10.CT tu 054 1000326083 PHI THI VIET DUC toi 067 0190997777 NGUYEN THI HUYEN tai MB- | G154: NGUYEN THI HUYEN | H154: 670190997777 | I154: MB
A155: 138 | B155: 30/10/2025 21:16 | C155: FT25303874122089 | D155: 0 | E155: 800000 | F155: VU VAN NGUYEN VU THI THANH PHUONG SV11X1X19 THANG 10- Ma GD ACSP/ k9461272 | G155: NGUYEN THI HUYEN | H155: 670190997777 | I155: MB
...

Sheet Data_HS t5
A1: Stt | B1: Hovaten | C1: ID_Lop
A2: 1 | B2: Nguyễn Đăng Khôi | C2: SV10.1.1 | D2: 14/07/2009 | E2: Nam | F2: 0921916686 | G2: Nguyễn Tiến Mạnh | H2: 0913123399 | I2: Nguyễn Thị Quỳnh Hương | J2: 0921916686 | K2: Tổ dân phố số 14, Phường Việt Hưng, Quận Long Biên, Thành phố Hà Nội
A3: 2 | B3: Nguyễn Gia Kỳ | C3: SV10.1.2 | D3: 22/08/2009 | E3: Nam | F3: 0978392117 | G3: Nguyễn Đức Cường | H3: 0915190258 | I3: Chu Thị Mỹ Châu | J3: 0978392117 | K3: Tổ dân phố số 10, Phường Cự Khối, Quận Long Biên, Thành phố Hà Nội
A4: 3 | B4: Hoàng Minh Quân | C4: SV10.1.3 | D4: 30/09/2009 | E4: Nam | F4: 0943606816 | G4: Hoàng Văn Quyền | H4: 0915830909 | I4: Đặng Quỳnh Trang | J4: 0943606816 | K4: Tổ dân phố số 1, Phường Cự Khối, Quận Long Biên, Thành phố Hà Nội
A5: 4 | B5: Phạm Chí Thiên | C5: SV10.1.4 | D5: 01/09/2009 | E5: Nam | F5: 0774299474 | G5: Phạm Văn An | H5: 0908780506 | I5: Nguyễn Thị Như Quỳnh | J5: 0774299474 | K5: Tổ dân phố số 2, Phường Ngọc Lâm, Quận Long Biên, Thành phố Hà Nội
A6: 5 | B6: Nguyễn Vũ Minh Anh | C6: SV10.1.5 | D6: 13/05/2009 | E6: Nữ | F6: 0982790289 | G6: Nguyễn Minh Mẫn | H6: 0 | I6: Vũ Hồng Giang | J6: 0982790289 | K6: Phường Ngọc Lâm, Quận Long Biên, Thành phố Hà Nội
I7: Trương Thị Tho | J7: 0902124589 | K7: Tổ dân phố 6, Phường Trúc Bạch, Quận Ba Đình, Thành phố Hà Nội
I8: Nguyễn Thị Mai | J8: 0898575223 | K8: Tổ dân phố An Lạc, Thị trấn Trâu Quỳ, Huyện Gia Lâm, Thành phố Hà Nội
I9: Chu Thị Thu Hương | J9: 0967351852 | K9: Tổ dân phố số 1, Phường Cự Khối, Quận Long Biên, Thành phố Hà Nội
I10: Trần Hồng Minh | J10: 0865495521 | K10: Phường Thạch Bàn, Quận Long Biên, Thành phố Hà Nội
I11: Dương Thị Tuyết Trinh | J11: 0399363261 | K11: Phường Thạch Bàn, Quận Long Biên, Thành phố Hà Nội
I16: Nguyễn Thị Hằng | J16: 0983310980 | K16: Tổ dân phố số 15, Phường Sài Đồng, Quận Long Biên, Thành phố Hà Nội
I17: Đỗ Thị Phương | J17: 0942479345 | K17: Tổ dân phố số 1, Phường Cự Khối, Quận Long Biên, Thành phố Hà Nội
I18: Lưu Phương Dung | J18: 0975375588 | K18: Phường Việt Hưng, Quận Long Biên, Thành phố Hà Nội
I19: Vũ Thị Thu Hương | J19: 0862793108 | K19: Tổ dân phố số 4, Xã Đặng Xá, Huyện Gia Lâm, Thành phố Hà Nội
I20: Nguyễn Thị Bích Phương | J20: 0915225659 | K20: Phường Đức Giang, Quận Long Biên, Thành phố Hà Nội
I21: Trần Thị Huyền | J21: 0985477918 | K21: Tổ dân phố số 7, Phường Ngọc Thụy, Quận Long Biên, Thành phố Hà Nội
I22: Nguyễn Thị Hiền | J22: 0961227887 | K22: Phường Sài Đồng, Quận Long Biên, Thành phố Hà Nội
... I28: ĐỖ THỊ HOA | J28: 0947246556 | K28: 29 ngõ 71 tổ 4 thạch bàn long biên hà nôi
I29: #N/A | J29: #N/A | K29: #N/A
I30: Nguyễn Thị Thanh Thủy | J30: 0946228884 | K30: Tổ 9 - Thạch Bàn - Long Biên- Hà Nội
I31: #N/A | J31: #N/A | K31: #N/A
I32: NGÔ THỊ THANH HƯƠNG | J32: 0397661482 | K32: Tổ 10, Phường Thạch Bàn, Quận Long Biên, TP Hà Nội
I33: Nguyễn Thị Trà Giang | J33: 0366879386 | K33: Tổ 9, Thạch Bàn, Long Biên, Hà Nội
I34: Nguyễn Thị Hoa | J34: 0372664026 | K34: Số 16/ 640/ 41 Nguyễn Văn Cừ ,Gia Thụy, Long Biên, Hà Nội
I35: #N/A | J35: #N/A | K35: #N/A
I36: Lò Thị Quỳnh Lan | J36: 0389981982 | K36: Lk26- khu đất đấu giá tổ 11, Phường Thạch Bàn, Quận Long Biên, Hà Nội
I37: Nguyễn Thị Hải Lệ | J37: 0916562655 | K37: Tổ dân phố số 12, Phường Ngọc Lâm, Quận Long Biên, Thành phố Hà Nội
I38: Bùi Thị Hồng Thúy | J38: 0 | K38: Tổ dân phố số 9, Phường Phúc Lợi, Quận Long Biên, Thành phố Hà Nội
I39: Trần Thị Thu | J39: 0972825402 | K39: Tổ dân phố số 3, Phường Cự Khối, Quận Long Biên, Thành phố Hà Nội
I40: Lê Thị Thành | J40: 0961270550 | K40: Tổ 17, Phường Bồ Đề, Quận Long Biên, Thành phố Hà Nội
I41: Đỗ Thị Hương Lan | J41: 0946397747 | K41: Tổ dân phố số 11, Phường Bồ Đề, Quận Long Biên, Thành phố Hà Nội
I42: Nguyễn Thị Hồ Lý | J42: 0988390863 | K42: Tổ dân phố An Lạc, Thị trấn Trâu Quỳ, Huyện Gia Lâm, Thành phố Hà Nội
I43: Lê Thị Duyên | J43: 0986318058 | K43: Thôn 5, Xã Đông Dư, Huyện Gia Lâm, Thành phố Hà Nội
I44: Nguyễn Thị Thu Hà | J44: 0901435688 | K44: Số 5/23 Vũ Xuân Thiều, Phường Phúc Lợi, Quận Long Biên, Thành phố Hà Nội
I45: Nguyễn Thị Huệ | J45: 0978413159 | K45: Tổ 10, Phường Thạch Bàn, Quận Long Biên, Thành phố Hà Nội
I46: Nguyễn Phương Anh | J46: 0948679879 | K46: Phường Sài Đồng, Quận Long Biên, Thành phố Hà Nội
I47: Nguyễn Thị Kỷ | J47: 0389995665 | K47: Tổ dân phố số 38, Phố Bắc Cầu, Phường Ngọc Thụy, Quận Long Biên, Thành phố Hà Nội
I48: Đặng Thị Hồng Vân | J48: 0962768236 | K48: Tổ dân phố số 17, Phường Ngọc Thụy, Quận Long Biên, Thành phố Hà Nội
I49: Nguyễn Thị Ngoan | J49: 0934582291 | K49: Tổ dân phố số 2, Phường Giang Biên, Quận Long Biên, Thành phố Hà Nội
I50: Trần Thị Thanh Hiền | J50: 0984571256 | K50: Chung cư Eurowindow River Park, Xã Đông Hội, Huyện Đông Anh, Thành phố Hà Nội
... I57: Trần Thị Ái Vân | J57: 0349652368 | K57: Thôn Ngọc Động, Xã Đa Tốn, Huyện Gia Lâm, Thành phố Hà Nội
I58: 0 | J58: 0 | K58: 0
I59: Trần Thị Thanh Trang | J59: 0942686085 | K59: Tổ 4, Phường Hàng Buồm, Quận Hoàn Kiếm, Thành phố Hà Nội
I60: Vũ Huyền Hạnh | J60: 0945428989 | K60: Tổ 02, Phường Hàng Bông, Quận Hoàn Kiếm, Thành phố Hà Nội
I61: #N/A | J61: #N/A | K61: #N/A
A62: 16 | B62: FT25303928106845 | C62: SV10.4.16 | D62: 27/09/2009 | E62: Nam | F62: 0948221138 | G62: Tạ Đình Khánh | H62: 0 | I62: Lê Thị Thu Huyền | J62: 0948221138 | K62: 233 Nguyễn Văn Cừ, Long Biên, Hà Nội
A63: 1 | B63: Nguyễn Quang Anh | C63: SV10.8.1 | D63: 21/07/2009 | E63: Nam | F63: 0963616933 | G63: Nguyễn Xuân Hoè | H63: 0969216777 | I63: Ngô Thị Vĩnh Hà | J63: 0 | K63: Tổ 10, phường Bồ đề
A64: 2 | B64: Nguyễn Vũ Ngọc Anh | C64: SV10.8.2 | D64: 02/08/2009 | E64: Nữ | F64: 0879150722 | G64: Nguyễn Hiếu Phi | H64: 0 | I64: Vũ Thị Kim Thoa | J64: 0 | K64: số 52, ngách 268/56, Ngọc Thụy, Long Biên
A65: 3 | B65: Đào Yến Chi | C65: SV10.8.3 | D65: 24/07/2009 | E65: Nữ | F65: 0936002827 | G65: Đào Văn Cường | H65: 0904800555 | I65: Nguyễn Thị Kim Tuyến | J65: 0972300649 | K65: Tổ 5, Phúc Đồng
A66: 4 | B66: Nguyễn Thùy Dương | C66: SV10.8.4 | D66: 21/08/2009 | E66: Nữ | F66: 0981694611 | G66: Nguyễn Thanh Quế | H66: 0984601093 | I66: Hoàng Thị Lan | J66: 0983335955 | K66: Số nhà 18C, ngõ 75 Phố Cầu Đất - Phường Chương Dương - Q. Hoàn Kiếm - Hà Nội
A67: 5 | B67: Bùi Gia Huy | C67: SV10.8.5 | D67: 27/09/2009 | E67: Nam | F67: 0899405766 | G67: Bùi Văn Hiền | H67: 0944629983 | I67: Lê Thị Bích Ngọc | J67: 0 | K67: số 66 ngõ 1 tổ 25 phường Bồ Đề. Long Biên- Hà Nội
A68: 6 | B68: Văn Đức Khánh | C68: SV10.8.6 | D68: 20/08/2009 | E68: Nam | F68: 0985076000 | G68: Văn Đình Chiến | H68: 0902610261 | I68: Trần Thị Hà | J68: 0 | K68: Tổ 15 phường Sài Đồng Quận Long Biên TP Hà Nội
A69: 7 | B69: Trương Bá Bảo Nam | C69: SV10.8.7 | D69: 15/08/2009 | E69: Nam | F69: 0818659222 | G69: Trương Bá Quyền | H69: 0969232888 | I69: Trần Thị Thu Thuận | J69: 0 | K69: Tổ dân phố số 6, Phường Việt Hưng, Quận Long Biên, Thành phố Hà Nội
A70: 8 | B70: Nguyễn Tùng Quân | C70: SV10.8.8 | D70: 09/02/2009 | E70: Nam | F70: 0967510785 | G70: Nguyễn Quang Anh | H70: 0942619339 | I70: Trần Bích Thuỷ | J70: 0912304482 | K70: 29/92 Phố Trạm Phường Long Biên
A71: 9 | B71: Trần Ngọc Bảo Trâm | C71: SV10.8.9 | D71: 03/12/2009 | E71: Nữ | F71: 0865977174 | G71: Trần Ngọc Dũng | H71: 0981193679 | I71: Nguyễn Thị Lan Anh | J71: 0 | K71: Phòng 609 Chung cư ct2a Tổ 17 - Thạch Bàn
A72: 10 | B72: Phạm Hoàng Minh Trúc | C72: SV10.8.10 | D72: 15/01/2009 | E72: Nữ | F72: 0961014569 | G72: Phạm Đăng Linh | H72: 0914508980 | I72: Nguyễn Hoàng Yến | J72: 0914058840 | K72: Phường Vĩnh Tuy
A73: 1 | B73: Nguyễn Ngọc Thành An | C73: SV10.9.1 | D73: 07/08/2009 | E73: 0 | F73: 0978183285 | G73: 0 | H73: 0 | I73: 0 | J73: 0 | K73: Tổ 8, Phường Ngọc Thụy, Quận Long Biên, Thành phố Hà Nội
A74: 2 | B74: Lê Minh Bắc | C74: SV10.9.2 | D74: 16/08/2009 | E74: 0 | F74: 0345776310 | G74: 0 | H74: 0 | I74: 0 | J74: 0 | K74: Phường Đức Giang, Quận Long Biên, Thành phố Hà Nội
A75: 4 | B75: Nguyễn Mai Chi | C75: SV10.9.4 | D75: 20/07/2009 | E75: 0 | F75: 0984167357 | G75: 0 | H75: 0 | I75: 0 | J75: 0 | K75: Phường Phúc Tân, Quận Hoàn Kiếm, Thành phố Hà Nội
A76: 5 | B76: Lê Minh Giang | C76: SV10.9.5 | D76: 16/01/2009 | E76: 0 | F76: 0375280813 | G76: 0 | H76: 0 | I76: 0 | J76: 0 | K76: Phường Phúc Đồng, Quận Long Biên, Thành phố Hà Nội
A77: 6 | B77: Phạm Hùng Giang | C77: SV10.9.6 | D77: 22/10/2009 | E77: 0 | F77: 0913447315 | G77: 0 | H77: 0 | I77: 0 | J77: 0 | K77: Phường Sài Đồng, Quận Long Biên, Thành phố Hà Nội
A78: 7 | B78: Vũ Thúy Hằng | C78: SV10.9.7 | D78: 27/11/2009 | E78: 0 | F78: 0973174939 | G78: 0 | H78: 0 | I78: 0 | J78: 0 | K78: Tổ dân phố Chính Trung, Thị trấn Trâu Quỳ, Huyện Gia Lâm, Thành phố Hà Nội
A79: 8 | B79: Phạm Quang Hợp | C79: SV10.9.8 | D79: 19/02/2009 | E79: 0 | F79: 0982011808 | G79: 0 | H79: 0 | I79: 0 | J79: 0 | K79: Tổ 8, Phường Bồ Đề, Quận Long Biên, Thành phố Hà Nội
A80: 9 | B80: Hoàng Quang Huy | C80: SV10.9.9 | D80: 19/12/2009 | E80: 0 | F80: 0389849319 | G80: 0 | H80: 0 | I80: 0 | J80: 0 | K80: Tổ 34, Phường Ngọc Thụy, Quận Long Biên, Thành phố Hà Nội
A81: 11 | B81: Đàm Nguyên Khánh | C81: SV10.9.11 | D81: 31/07/2009 | E81: 0 | F81: 0923291999 | G81: 0 | H81: 0 | I81: 0 | J81: 0 | K81: Phường Phúc Đồng, Quận Long Biên, Thành phố Hà Nội
A82: 14 | B82: Nguyễn Tùng Lâm | C82: SV10.9.14 | D82: 05/03/2009 | E82: 0 | F82: 0978427268 | G82: 0 | H82: 0 | I82: 0 | J82: 0 | K82: Phường Gia Thụy, Quận Long Biên, Thành phố Hà Nội
A83: 16 | B83: Nguyễn Ngọc Quỳnh | C83: SV10.9.16 | D83: 31/12/2009 | E83: 0 | F83: 0984715792 | G83: 0 | H83: 0 | I83: 0 | J83: 0 | K83: Phường Thạch Bàn, Quận Long Biên, Thành phố Hà Nội
A84: 18 | B84: Lương Thanh Thảo | C84: SV10.9.18 | D84: 05/09/2009 | E84: 0 | F84: 0913092784 | G84: 0 | H84: 0 | I84: 0 | J84: 0 | K84: Phường Bồ Đề, Quận Long Biên, Thành phố Hà Nội
... A86: 20 | B86: Phạm Anh Tuấn | C86: SV10.9.20 | D86: 25/09/2009 | E86: 0 | F86: 0369004580 | G86: 0 | H86: 0 | I86: 0 | J86: 0 | K86: Phường Thạch Bàn, Quận Long Biên, Thành phố Hà Nội
A87: 1 | B87: Đinh Phương Anh | C87: SV10.15.1 | D87: 27/02/2009 | E87: Nữ | F87: 0869719793 | G87: Đinh Quý Tài | H87: 0914887628 | I87: Vũ Hồng Hải | J87: *0947362528 | K87: Số nhà 44, ngõ 81, tổ 12, phố Trạm, Long Biên, HN
A88: 2 | B88: Nguyễn Hoàng Anh | C88: SV10.15.2 | D88: 21/09/2009 | E88: Nam | F88: 0916616716 | G88: Nguyễn Văn Tuấn | H88: 0973971366 | I88: Phan Thị Thanh | J88: *0916610038 | K88: Số 10 ngách 127/17/20 Phúc Xá, Q. Ba Đình, HN
A89: 3 | B89: Vương Phương Anh | C89: SV10.15.3 | D89: 15/01/2009 | E89: Nữ | F89: 0387346638 | G89: Vương Đình Tĩnh | H89: 0972870380 | I89: Vũ Thị Hải | J89: 0985404829 | K89: Căn 605 Ct2b Lô No23,Thượng Thanh,Long Biên,Hà Nội
A90: 4 | B90: Hoàng Giang Ánh | C90: SV10.15.4 | D90: 28/11/2009 | E90: Nữ | F90: 0945622988 | G90: Hoàng Vĩnh Tùng | H90: 0902199180 | I90: Kiều Thanh Nga | J90: 0918098860 | K90: C17 Bộ Công an Ngõ 264/63 Ngọc Thụy - Long Biên,HN
A91: 5 | B91: Nguyễn Thu Hà | C91: SV10.15.5 | D91: 40037 | E91: Nữ | F91: 0943668818 | G91: Nguyễn Văn Hải | H91: 0942668919 | I91: Nguyễn Thị Thanh Huyền | J91: 0915655505 | K91: P12A12 NO11A khu đô thị Sài Đồng Long Biên Hà Nội
A92: 6 | B92: Hoàng Gia Huy | C92: SV10.15.6 | D92: 39968 | E92: Nam | F92: 0964722364 | G92: Hoàng Ngọc Hà | H92: 0916957100 | I92: Phạm Thị Hoan | J92: 0395480708 | K92: Tổ 13 ngách 195/16/10 Phúc Lợi,Long Biên,Hà Nội
A93: 7 | B93: Nguyễn Gia Huy | C93: SV10.15.7 | D93: 25/03/2009 | E93: Nam | F93: 0374706623 | G93: Nguyễn Đình Hùng | H93: Đã mất | I93: Vũ Ngọc Bích | J93: 0984942835 | K93: Căn hộ 703, D12, Tổ 15, phường Sài Đồng, Long Biên, HN
A94: 8 | B94: Nguyễn Gia Hưng | C94: SV10.15.8 | D94: 19/11/2009 | E94: Nam | F94: 0842191109 | G94: Nguyễn Bá Ngọc | H94: 0942299907 | I94: Phạm Lan Anh | J94: 0943903183 | K94: Số 14 ngách 110 ngoc 640 Nguyễn Văn Cừ, phường Gia Thuỵ, Long Biên, Hà Hội
A95: 9 | B95: Trần Duy Long | C95: SV10.15.9 | D95: 29/10/2009 | E95: Nam | F95: 097 8432855 | G95: Trần Đình Thu | H95: 0983333011 | I95: Lê Thị Thu Dung | J95: 0366607982 | K95: Số nhà 13 ngõ 78/79 tổ 8 phường Bồ Đề , Long Biên ,Hà Nội
A96: 10 | B96: Lê Bảo Khánh Ly | C96: SV10.15.10 | D96: 28/01/2009 | E96: Nữ | F96: 0865907695 | G96: Lê Đình Minh | H96: 0975859090 | I96: Thái Thị Hoà | J96: 0975469090 | K96: Số 5 Hoàng Như Tiếp Bồ Đề Long Biên Hà Nội
A97: 11 | B97: Hoàng Phương Mai | C97: SV10.15.11 | D97: 27/11/2009 | E97: Nữ | F97: 0399462990 | G97: Hoàng Văn Trọng | H97: 0912126457 | I97: Trần Thị Thanh | J97: 0357599688 | K97: Số 105 đường Cổ Linh, tổ 10, Thạch Bàn, Long Biên, Hà Nội
A98: 12 | B98: Lưu Xuân Mai | C98: SV10.15.12 | D98: 14/01/2009 | E98: Nữ | F98: 0379801992 | G98: Lưu Xuân Tâm | H98: 0978255788 | I98: Nguyễn Thị Hoàng Điệp | J98: 0906002400 | K98: 28/640/21/16 Nguyễn Văn Cừ Tổ 13, Gia Thụy, Long Biên, Hà Nội
A99: 13 | B99: Dương Hạnh Minh | C99: SV10.15.13 | D99: 40067 | E99: Nữ | F99: `0775455591 | G99: Dương Ngọc Thành | H99: 0914603888 | I99: Lưu Thị Hồng Hạnh | J99: 0904245880 | K99: Số 20 phố Thạch Bàn, tổ 3 phường Thạch Bàn, quận Long Biên, Hà Nội
A100: 15 | B100: Nguyễn Tú Quyên | C100: SV10.15.15 | D100: 20/11/2009 | E100: Nữ | F100: 0816061699 | G100: Nguyễn Thế Anh | H100: 0915658968 | I100: Nguyễn Thị Lệ Hằng | J100: 0915892636 | K100: Số 8, Ngõ 158, Nguyễn Văn Cừ, Tổ 3, phường Bồ Đề, quận Long Biên, Tp Hà Nội
A101: 16 | B101: Phạm Nhật Thảo | C101: SV10.15.16 | D101: 02/12/2009 | E101: Nữ | F101: 0705632863 | G101: Phạm Quốc Ân | H101: 0949999568 | I101: Hứa Thị Nội | J101: 0906081208 | K101: Số 21, ngách 7a, ngõ 377 Lâm Du- Tổ 12 - Phường Bồ Đề - Q. Long Biên- HN
A102: 17 | B102: Nguyễn Hà Thu | C102: SV10.15.17 | D102: 39975 | E102: Nữ | F102: Không dùng | G102: Nguyễn Đức Lợi | H102: 0904222276 | I102: Nguyễn Thị Thu Hà | J102: 0942697611 | K102: Số 9, Trương Hán Siêu, Trần Hưng Đạo, Hoàn Kiếm, Hà Nội
A103: 18 | B103: Nguyễn Tuấn Việt | C103: SV10.15.18 | D103: 40037 | E103: Nam | F103: 0814759607 | G103: Nguyễn Minh Tuấn | H103: Ly hôn | I103: Nguyễn Thị Hải Ly | J103: 0916587117 | K103: Số 6 Ngõ 548/40 Nguyễn Văn Cừ, Phường Gia Thụy, Quận Long Biên, Hà Nội
A104: 19 | B104: Nguyễn Đăng Việt | C104: SV10.15.19 | D104: #N/A | E104: #N/A | F104: #N/A | G104: #N/A | H104: #N/A | I104: #N/A | J104: #N/A | K104: #N/A
A105: 22 | B105: Đinh Thanh Thảo | C105: SV10.15.22 | D105: 19/02/2009 | E105: Nữ | F105: 0397969194 | G105: Đinh Đình Khoa | H105: 0979324726 | I105: Chu Thị Thanh Huyền | J105: 0986091922 | K105: Số 640 đường Ngọc Lâm, tổ 5, P. Gia Thụy, Long Biên, HN
A106: 23 | B106: Nguyễn Minh Ánh | C106: SV10.15.23 | D106: 26/10/2009 | E106: Nữ | F106: 0886271132 | G106: Nguyễn Văn Sơn | H106: 0949564568 | I106: Đỗ Thu Vân | J106: 0942041468 | K106: Ngách 15/66 Đàm Quang Trung, Long Biên, Hà Nội
A107: 25 | B107: Nguyễn Đăng Việt | C107: SV10.15.25 | D107: #N/A | E107: #N/A | F107: #N/A | G107: #N/A | H107: #N/A | I107: #N/A | J107: #N/A | K107: #N/A
A108: 26 | B108: Nguyễn Minh Đăng | C108: SV10.15.26 | D108: #N/A | E108: #N/A | F108: #N/A | G108: #N/A | H108: #N/A | I108: #N/A | J108: #N/A | K108: #N/A
A109: 29 | B109: Đỗ Thị Diệu Nga | C109: SV10.15.29 | D109: #N/A | E109: #N/A | F109: #N/A | G109: #N/A | H109: #N/A | I109: #N/A | J109: #N/A | K109: #N/A
A110: 1 | B110: Nguyễn Vũ Mai Anh | C110: SV11.1.1 | D110: 07/01/2008 | E110: Nữ | F110: 0886894009 | G110: Nguyễn Thanh Toàn | H110: 0 | I110: Vũ Thị Hiền | J110: 0886894009 | K110: Tổ dân phố số 5, Phường Long Biên, Quận Long Biên, Thành phố Hà Nội
A111: 2 | B111: Võ Bảo Anh | C111: SV11.1.2 | D111: 27/05/2008 | E111: Nữ | F111: 0983123167 | G111: Võ Anh Dũng | H111: 0989123167 | I111: Trần Thị Thu | J111: 0983123167 | K111: Phường Thanh Trì, Quận Hoàng Mai, Thành phố Hà Nội
A112: 3 | B112: Nguyễn Thanh Bình | C112: SV11.1.3 | D112: 21/12/2008 | E112: Nam | F112: 0779323289 | G112: Nguyễn Văn Luyến | H112: 0 | I112: Nguyễn Thị Thập | J112: 0 | K112: Phường Thạch Bàn, Quận Long Biên, Thành phố Hà Nội
A113: 4 | B113: Lưu Minh Châu | C113: SV11.1.4 | D113: 23/04/2008 | E113: Nữ | F113: 0976787198 | G113: Lưu Khánh Dương | H113: 0913230517 | I113: Phùng Thu Hiền | J113: 0976787198 | K113: Tổ dân phố số 20, Phường Đức Giang, Quận Long Biên, Thành phố Hà Nội
A114: 5 | B114: Bùi Vĩnh Đại | C114: SV11.1.5 | D114: 12/10/2008 | E114: Nam | F114: 0932398189 | G114: Bùi Hải Hà | H114: 0933116686 | I114: Nguyễn Thị Ngọc Vân | J114: 0932398189 | K114: Tổ dân phố số 18, Phường Ngọc Thụy, Quận Long Biên, Thành phố Hà Nội
A115: 6 | B115: Nguyễn Minh Đức | C115: SV11.1.6 | D115: 30/12/2008 | E115: Nam | F115: 0976668112 | G115: Nguyễn Văn Sự | H115: 0903060986 | I115: Phạm Thị Nguyệt | J115: 0976668112 | K115: TT Cầu 12, Thôn Hội, Xã Cổ Bi, Huyện Gia Lâm, Thành phố Hà Nội.
A116: 7 | B116: Đỗ Thu Hiền | C116: SV11.1.7 | D116: 06/10/2008 | E116: Nữ | F116: 0947592068 | G116: Đỗ Trọng Sơn | H116: 0 | I116: Mai Thị Thanh Quỳnh | J116: 0947592068 | K116: Phường Thạch Bàn, Quận Long Biên, Thành phố Hà Nội
...

Sheet Data_HS t9
A1: Stt | B1: Hovaten | C1: ID_Lop | D1: sinh ngày | E1: giới tính | F1: sdt1 | G1: Bố | H1: SDt2 | I1: Mẹ | J1: sdt 3 | K1: Địa chỉ
A2: 1 | B2: Đinh Nguyên Dương | C2: SV11.1.1 | D2: 01/02/2009 | E2: Nam | F2: 0987218698 | G2: Đinh Quang Sơn | H2: 0968355949 | I2: Nguyễn Thị Quyên | J2: 0987218698 | K2: Tổ dân phố số 36, Phường Ngọc Thụy, Quận Long Biên, Thành phố Hà Nội
A3: 2 | B3: Hoàng Khánh Nam | C3: SV11.1.2 | D3: 03/09/2009 | E3: Nam | F3: 0961227887 | G3: Hoàng Văn Khánh | H3: 0912095104 | I3: Nguyễn Thị Hiền | J3: 0961227887 | K3: Phường Sài Đồng, Quận Long Biên, Thành phố Hà Nội
A4: 3 | B4: Hoàng Minh Quân | C4: SV11.1.3 | D4: 30/09/2009 | E4: Nam | F4: 0943606816 | G4: Hoàng Văn Quyền | H4: 0915830909 | I4: Đặng Quỳnh Trang | J4: 0943606816 | K4: Tổ dân phố số 1, Phường Cự Khối, Quận Long Biên, Thành phố Hà Nội
A5: 4 | B5: Nghiêm Thành Đạt | C5: SV11.1.4 | D5: 28/04/2009 | E5: Nam | F5: 0985477918 | G5: Nghiêm Phú Cường | H5: 0985477918 | I5: Trần Thị Huyền | J5: 0985477918 | K5: Tổ dân phố số 7, Phường Ngọc Thụy, Quận Long Biên, Thành phố Hà Nội
A6: 5 | B6: Nghiêm Xuân Bảo Minh | C6: SV11.1.5 | D6: 12/02/2009 | E6: Nam | F6: 0975375588 | G6: Nghiêm Xuân Khánh | H6: 0366607004 | I6: Lưu Phương Dung | J6: 0975375588 | K6: Phường Việt Hưng, Quận Long Biên, Thành phố Hà Nội
A7: 6 | B7: Nguyễn Đăng Khôi | C7: SV11.1.6 | D7: 14/07/2009 | E7: Nam | F7: 0921916686 | G7: Nguyễn Tiến Mạnh | H7: 0913123399 | I7: Nguyễn Thị Quỳnh Hương | J7: 0921916686 | K7: Tổ dân phố số 14, Phường Việt Hưng, Quận Long Biên, Thành phố Hà Nội
A8: 7 | B8: Nguyễn Gia Khoa | C8: SV11.1.7 | D8: 05/12/2009 | E8: Nam | F8: 0916187589 | G8: Nguyễn Thanh Hùng | H8: 0916187589 | I8: Nguyễn Thị Mai | J8: 0898575223 | K8: Tổ dân phố An Lạc, Thị trấn Trâu Quỳ, Huyện Gia Lâm, Thành phố Hà Nội
A9: 8 | B9: Nguyễn Gia Kỳ | C9: SV11.1.8 | D9: 22/08/2009 | E9: Nam | F9: 0978392117 | G9: Nguyễn Đức Cường | H9: 0915190258 | I9: Chu Thị Mỹ Châu | J9: 0978392117 | K9: Tổ dân phố số 10, Phường Cự Khối, Quận Long Biên, Thành phố Hà Nội
A10: 9 | B10: Nguyễn Khánh Phương | C10: SV11.1.9 | D10: 24/11/2009 | E10: Nữ | F10: 0963284506 | G10: Nguyễn Quốc Đạt | H10: 0963284506 | I10: Nguyễn Thị Tuyết Hạnh | J10: 0989318075 | K10: Tổ dân phố An Đào, Thị trấn Trâu Quỳ, Huyện Gia Lâm, Thành phố Hà Nội
A11: 10 | B11: Nguyễn Phương Thủy | C11: SV11.1.10 | D11: 26/04/2009 | E11: Nữ | F11: 0916558877 | G11: Nguyễn Thế Hưng | H11: 0916558867 | I11: Trần Phương Thảo | J11: 0916558867 | K11: Tổ dân phố số 13, Phường Bồ Đề, Quận Long Biên, Thành phố Hà Nội
A12: 11 | B12: Nguyễn Thu Ngân | C12: SV11.1.11 | D12: 04/01/2009 | E12: Nữ | F12: 0989127588 | G12: Nguyễn Ngọc Thái | H12: 0989127588 | I12: Lê Thị Chi | J12: 0989127588 | K12: Tổ dân phố 10, Phường Phúc Xá, Quận Ba Đình, Thành phố Hà Nội
A13: 13 | B13: Nguyễn Vũ Minh Anh | C13: SV11.1.13 | D13: 13/05/2009 | E13: Nữ | F13: 0982790289 | G13: Nguyễn Minh Mẫn | H13: 0 | I13: Vũ Hồng Giang | J13: 0982790289 | K13: Phường Ngọc Lâm, Quận Long Biên, Thành phố Hà Nội
A14: 15 | B14: Phạm Gia Minh | C14: SV11.1.15 | D14: 14/11/2009 | E14: Nam | F14: 0913132268 | G14: Phạm Anh Đức | H14: 0913132268 | I14: Nguyễn Thị Loan | J14: 0368947535 | K14: Tổ 5, Phường Vĩnh Hưng, Quận Hoàng Mai, Thành phố Hà Nội
A15: 17 | B15: Trần Đức Anh | C15: SV11.1.17 | D15: 09/01/2009 | E15: Nam | F15: 0915225659 | G15: Trần Thanh Hùng | H15: 0912317676 | I15: Nguyễn Thị Bích Phương | J15: 0915225659 | K15: Phường Đức Giang, Quận Long Biên, Thành phố Hà Nội
A16: 18 | B16: Trần Khôi Nguyên | C16: SV11.1.18 | D16: 07/10/2009 | E16: Nam | F16: 0976596686 | G16: Trần Tuấn Anh | H16: 0978333878 | I16: Nguyễn Thị Hải | J16: 0976596686 | K16: Tổ dân phố số 2, Phường Long Biên, Quận Long Biên, Thành phố Hà Nội
A17: 19 | B17: Vũ Thị Thanh Phương | C17: SV11.1.19 | D17: 25/02/2009 | E17: Nữ | F17: 0898272016 | G17: Vũ Văn Nguyên | H17: 0898272016 | I17: Lê Thu Hương | J17: 0972762509 | K17: Tòa S1-01-02-03-05-06-07-08-09, Vinhome Ocean Park, Xã Đa Tốn, Huyện Gia Lâm, Thành phố Hà Nội
A18: 21 | B18: Lê Ngọc Như Anh | C18: SV11.1.21 | D18: 26/04/2009 | E18: Nữ | F18: 0862793108 | G18: Lê Tiến Dũng | H18: 0986130707 | I18: Vũ Thị Thu Hương | J18: 0862793108 | K18: Tổ dân phố số 4, Xã Đặng Xá, Huyện Gia Lâm, Thành phố Hà Nội
A19: 1 | B19: Hoàng Khánh Linh Anh | C19: SV11.2.1 | D19: 40098 | E19: Nữ | F19: 0923832012 | G19: Hoàng Tâm | H19: 0913313131 | I19: Nguyễn Thị Thanh Thủy | J19: 0946228884 | K19: Tổ 9 - Thạch Bàn - Long Biên- Hà Nội
A20: 2 | B20: Khổng Quốc An | C20: SV11.2.2 | D20: 40060 | E20: Nam | F20: 0582016768 | G20: KHỔNG ĐÌNH HƯNG | H20: 0913564546 | I20: ĐỖ THỊ HOA | J20: 0947246556 | K20: 29 ngõ 71 tổ 4 thạch bàn long biên hà nôi
A21: 3 | B21: Lê Mạc Thuỳ Trinh | C21: SV11.2.3 | D21: #N/A | E21: #N/A | F21: #N/A | G21: #N/A | H21: #N/A | I21: #N/A | J21: #N/A | K21: #N/A
A22: 4 | B22: Lương Đức Huy | C22: SV11.2.4 | D22: 40135 | E22: Nam | F22: 0833171519 | G22: Lương Thanh Hiếu | H22: 0912445906 | I22: Vũ Kim Ngân | J22: 0947011800 | K22: Thạch Bàn, Long Biên, Hà Nội
A23: 5 | B23: Lương Ngọc Vy | C23: SV11.2.5 | D23: 39937 | E23: Nữ | F23: 0869702665 | G23: Lương Ngọc Lân | H23: 0975278268 | I23: Vũ Hoàng Anh | J23: 0977883636 | K23: Số 41A/62 Hoàng Như Tiếp, Bồ Đề, Long Biên, Hà Nội
A24: 6 | B24: Lưu Tường Mai Phương | C24: SV11.2.6 | D24: #N/A | E24: #N/A | F24: #N/A | G24: #N/A | H24: #N/A | I24: #N/A | J24: #N/A | K24: #N/A
A25: 7 | B25: Nguyễn Duy Dũng | C25: SV11.2.7 | D25: 39856 | E25: Nam | F25: 0879993643 | G25: Nguyễn Duy Giang | H25: 0888702868 | I25: Nguyễn Thị Trang | J25: 0946820088 | K25: Số nhà 6c, ngõ 39, phố Ngọc Trì, Thạch Bàn, Long Biên, Hà Nội
A26: 8 | B26: Nguyễn Hải Nam | C26: SV11.2.8 | D26: 40028 | E26: Nam | F26: 0338143817 | G26: Nguyễn Nam Hải | H26: 0988484285 | I26: Nguyễn Phương Thúy | J26: 0963999386 | K26: Tổ dân phố An Lạc, TT Trâu Quỳ, Gia Lâm, Hà Nội
A27: 9 | B27: Nguyễn Hữu Nam | C27: SV11.2.9 | D27: 40072 | E27: Nam | F27: 0337635606 | G27: Nguyễn Hữu Phương | H27: 0968501111 | I27: Lò Thị Quỳnh Lan | J27: 0389981982 | K27: Lk26- khu đất đấu giá tổ 11, Phường Thạch Bàn, Quận Long Biên, Hà Nội
A28: 10 | B28: Nguyễn Khánh An | C28: SV11.2.10 | D28: #N/A | E28: #N/A | F28: #N/A | G28: #N/A | H28: #N/A | I28: #N/A | J28: #N/A | K28: #N/A
A29: 11 | B29: Nguyễn Minh Phúc | C29: SV11.2.11 | D29: 40081 | E29: Nam | F29: 0393486494 | G29: Nguyễn Thanh Sơn | H29: 0936738067 | I29: Lê Thị Lưu | J29: 0389252265 | K29: An Lạc. Trâu Quỳ, Gia Lân, Hà Nội
A30: 12 | B30: Nguyễn Thị Minh Hằng | C30: SV11.2.12 | D30: 40103 | E30: Nữ | F30: 0396399209 | G30: Nguyễn Thế Thành | H30: 0366823044 | I30: Nguyễn Thị Hoa | J30: 0372664026 | K30: Số 16/ 640/ 41 Nguyễn Văn Cừ ,Gia Thụy, Long Biên, Hà Nội
A31: 14 | B31: Phạm Hiển Long | C31: SV11.2.14 | D31: #N/A | E31: #N/A | F31: #N/A | G31: #N/A | H31: #N/A | I31: #N/A | J31: #N/A | K31: #N/A
A32: 15 | B32: Phạm Thu Giang | C32: SV11.2.15 | D32: 39992 | E32: Nữ | F32: 0364200761 | G32: Phạm Văn Hậu | H32: 0988524552 | I32: Dương Thị Thu Hương | J32: 0986317405 | K32: Số 2, ngách 565/45, đường Bát Khối, tổ 10, Cự Khối, Long Biên, Hà Nội
A33: 16 | B33: Phan Quốc Anh | C33: SV11.2.16 | D33: 40078 | E33: Nam | F33: 0795088009 | G33: Phan Trung Thực | H33: 0912012209 | I33: Phạm Thị Thúy Hằng | J33: 0935115222 | K33: Chung cư quân đội ct1 thạch bàn long biên hà nội
A34: 17 | B34: Trần Đình Dũng | C34: SV11.2.17 | D34: 39832 | E34: Nam | F34: 081 558 2686 | G34: Trần Đình Kiên | H34: 0979 98 1289 | I34: Lương Thị Anh | J34: 091 6622 590 | K34: Số 9 , Hẻm 68/79/94 Nguyễn Văn Linh , Tổ 15 , Thạch Bàn , Long Biên ,Hà Nội
A35: 18 | B35: Trần Quang Hưng | C35: SV11.2.18 | D35: 39839 | E35: Nam | F35: 0335163695 | G35: TRẦN TUẤN QUANG | H35: 0914387952 | I35: BÙI THỊ THANH THẢO | J35: 0902101922 | K35: Tổ 21, phường Bồ Đề, Long Biên, Hà Nội
A36: 19 | B36: Trần Trọng Dũng | C36: SV11.2.19 | D36: 39910 | E36: Nam | F36: 0354569962 | G36: Trần Văn Tĩnh | H36: 0985103438 | I36: Bùi Thị Thắm | J36: 0354569962 | K36: P711, CC CT2A, Tổ 17, Thạch Bàn, Long Biên, Hà Nội
A37: 20 | B37: Trương Ngọc Vy | C37: SV11.2.20 | D37: 40024 | E37: Nữ | F37: 0962740810 | G37: TRƯƠNG HỒNG QUYẾT | H37: 0976178486 | I37: NGÔ THỊ THANH HƯƠNG | J37: 0397661482 | K37: Tổ 10, Phường Thạch Bàn, Quận Long Biên, TP Hà Nội
A38: 26 | B38: Vũ Minh Đức | C38: SV11.2.26 | D38: 0 | E38: 0 | F38: 0 | G38: 0 | H38: 0 | I38: 0 | J38: 0 | K38: 0
A39: 1 | B39: Đặng Phú Thái | C39: SV11.3.1 | D39: 26/09/2009 | E39: Nam | F39: 0389995665 | G39: Đặng Xuân Hải | H39: 0982998266 | I39: Nguyễn Thị Kỷ | J39: 0389995665 | K39: Tổ dân phố số 38, Phố Bắc Cầu, Phường Ngọc Thụy, Quận Long Biên, Thành phố Hà Nội
A40: 2 | B40: Đặng Quỳnh Chi | C40: SV11.3.2 | D40: 01/09/2009 | E40: Nữ | F40: 0912832779 | G40: Đặng Văn Vinh | H40: 0912832779 | I40: Bùi Thị Hồng Thúy | J40: 0 | K40: Tổ dân phố số 9, Phường Phúc Lợi, Quận Long Biên, Thành phố Hà Nội
A41: 4 | B41: Hà Xuân Việt Khánh | C41: SV11.3.4 | D41: 09/04/2009 | E41: Nam | F41: 0972675088 | G41: Hà Xuân Bộ | H41: 0972675088 | I41: Nguyễn Thị Hồ Lý | J41: 0988390863 | K41: Tổ dân phố An Lạc, Thị trấn Trâu Quỳ, Huyện Gia Lâm, Thành phố Hà Nội
A42: 5 | B42: Hoàng Việt Anh | C42: SV11.3.5 | D42: 28/04/2009 | E42: Nam | F42: 0963302009 | G42: Hoàng Ngọc Minh | H42: 0904050468 | I42: Trần Thị Hằng | J42: 0963302009 | K42: Tổ 13, Phường Thạch Bàn, Quận Long Biên, Thành phố Hà Nội
A43: 7 | B43: Lê Huy Sơn | C43: SV11.3.7 | D43: 06/06/2008 | E43: Nam | F43: 0965640210 | G43: Lê Việt Hùng | H43: 0965640210 | I43: Dương Thị Hoài Hương | J43: 0963349443 | K43: H4 Khu đô thị Việt Hưng, Phường Giang Biên, Quận Long Biên, Thành phố Hà Nội
A44: 8 | B44: Lê Minh Quang | C44: SV11.3.8 | D44: 20/11/2009 | E44: Nam | F44: 0989221972 | G44: Lê Quang Xuất | H44: 0989221972 | I44: Nguyễn Thị Thu Hương | J44: 0983969659 | K44: Tổ dân phố số 4, Phường Việt Hưng, Quận Long Biên, Thành phố Hà Nội
A45: 9 | B45: Mai Anh Quân | C45: SV11.3.9 | D45: 20/08/2009 | E45: Nam | F45: 0984110530 | G45: Mai Văn Toàn | H45: 0984110530 | I45: Phạm Thị Nghĩa | J45: 0975412282 | K45: Tổ dân phố số 12, Phường Long Biên, Quận Long Biên, Thành phố Hà Nội
A46: 11 | B46: Mai Nguyễn Thảo Nguyên | C46: SV11.3.11 | D46: 02/06/2009 | E46: Nữ | F46: 0978413159 | G46: Mai Quốc Hùng | H46: 0974131589 | I46: Nguyễn Thị Huệ | J46: 0978413159 | K46: Tổ 10, Phường Thạch Bàn, Quận Long Biên, Thành phố Hà Nội
A47: 12 | B47: Ngô Minh Quang | C47: SV11.3.12 | D47: #N/A | E47: #N/A | F47: #N/A | G47: #N/A | H47: #N/A | I47: #N/A | J47: #N/A | K47: #N/A
A48: 13 | B48: Nguyễn Bá Hải Bằng | C48: SV11.3.13 | D48: 20/02/2009 | E48: Nam | F48: 0912826750 | G48: Nguyễn Bá Hải | H48: 0912826750 | I48: Nguyễn Thị Hải Lệ | J48: 0916562655 | K48: Tổ dân phố số 12, Phường Ngọc Lâm, Quận Long Biên, Thành phố Hà Nội
A49: 14 | B49: Nguyễn Bùi Minh Đức | C49: SV11.3.14 | D49: 28/03/2009 | E49: Nam | F49: 0948394355 | G49: Nguyễn Văn Thao | H49: 0346455252 | I49: Bùi Thị Kim Oanh | J49: 0948394355 | K49: Tổ dân phố số 5, Phường Gia Thụy, Quận Long Biên, Thành phố Hà Nội
A50: 15 | B50: Nguyễn Đặng Cẩm Tú | C50: SV11.3.15 | D50: 30/01/2009 | E50: Nữ | F50: 0989832251 | G50: Nguyễn Huy Thanh | H50: 0989832251 | I50: Đặng Thị Hồng Vân | J50: 0962768236 | K50: Tổ dân phố số 17, Phường Ngọc Thụy, Quận Long Biên, Thành phố Hà Nội
A51: 17 | B51: Nguyễn Gia Duy | C51: SV11.3.17 | D51: 23/11/2009 | E51: Nam | F51: 0985138481 | G51: Nguyễn Quang Vinh | H51: 0932286821 | I51: Vũ Thị Dịu | J51: 0985138481 | K51: Tổ dân phố số 4, Phường Phúc Đồng, Quận Long Biên, Thành phố Hà Nội
A52: 18 | B52: Nguyễn Hạ Vy | C52: SV11.3.18 | D52: 10/06/2009 | E52: Nữ | F52: 0986886636 | G52: Nguyễn Văn Tứ | H52: 0334198668 | I52: Nguyễn Hồng Thủy | J52: 0986886638 | K52: Số 75, Tổ 12, Phường Phúc Lợi, Quận Long Biên, Thành phố Hà Nội.
A53: 19 | B53: Nguyễn Hoàng Mai | C53: SV11.3.19 | D53: 21/08/2009 | E53: Nữ | F53: 0382810968 | G53: Nguyễn Văn Lan | H53: 0382810968 | I53: Nguyễn Thị Quỳnh | J53: 0344388010 | K53: Tổ 10, Phường Thạch Bàn, Quận Long Biên, Thành phố Hà Nội
A54: 20 | B54: Nguyễn Minh Đức | C54: SV11.3.20 | D54: 27/11/2009 | E54: Nam | F54: 0946397747 | G54: Nguyễn Văn Hạnh | H54: 0936163136 | I54: Đỗ Thị Hương Lan | J54: 0946397747 | K54: Tổ dân phố số 11, Phường Bồ Đề, Quận Long Biên, Thành phố Hà Nội
A55: 22 | B55: Nguyễn Ngọc Quang Hải | C55: SV11.3.22 | D55: 19/09/2009 | E55: Nam | F55: 0985211911 | G55: Nguyễn Ngọc Hạ | H55: 0972488856 | I55: Trần Thị Phương Thảo | J55: 0985211911 | K55: Tổ dân phố 25, Phường Ngọc Thụy, Quận Long Biên, Thành phố Hà Nội
A56: 23 | B56: Nguyễn Thành Nam | C56: SV11.3.23 | D56: 07/11/2009 | E56: Nam | F56: 0901435688 | G56: Nguyễn Mạnh Đạt | H56: 0905435688 | I56: Nguyễn Thị Thu Hà | J56: 0901435688 | K56: Số 5/23 Vũ Xuân Thiều, Phường Phúc Lợi, Quận Long Biên, Thành phố Hà Nội
A57: 24 | B57: Nguyễn Thị Hải Vân | C57: SV11.3.24 | D57: 05/03/2009 | E57: Nữ | F57: 0934582291 | G57: Nguyễn Văn Phượng | H57: 0934484975 | I57: Nguyễn Thị Ngoan | J57: 0934582291 | K57: Tổ dân phố số 2, Phường Giang Biên, Quận Long Biên, Thành phố Hà Nội
A58: 25 | B58: Nguyễn Thị Kim Chi | C58: SV11.3.25 | D58: 21/05/2009 | E58: Nữ | F58: 0968504281 | G58: Nguyễn Đức Chí | H58: 0968504281 | I58: Trần Thị Thu | J58: 0972825402 | K58: Tổ dân phố số 3, Phường Cự Khối, Quận Long Biên, Thành phố Hà Nội
A59: 28 | B59: Nguyễn Trần Quang Vinh | C59: SV11.3.28 | D59: 0 | E59: 0 | F59: 0 | G59: 0 | H59: 0 | I59: 0 | J59: 0 | K59: 0
A60: 29 | B60: Nguyễn Tuấn Minh | C60: SV11.3.29 | D60: 0 | E60: 0 | F60: 0 | G60: 0 | H60: 0 | I60: 0 | J60: 0 | K60: 0
A61: 31 | B61: Trần Đức Anh | C61: SV11.3.31 | D61: 0 | E61: 0 | F61: 0 | G61: 0 | H61: 0 | I61: 0 | J61: 0 | K61: 0
A62: 32 | B62: Trần Khánh Linh | C62: SV11.3.32 | D62: 0 | E62: 0 | F62: 0 | G62: 0 | H62: 0 | I62: 0 | J62: 0 | K62: 0
A63: 33 | B63: Trần Nam Sơn | C63: SV11.3.33 | D63: 0 | E63: 0 | F63: 0 | G63: 0 | H63: 0 | I63: 0 | J63: 0 | K63: 0
A64: 35 | B64: Trần Thụy Trà Mi | C64: SV11.3.35 | D64: 0 | E64: 0 | F64: 0 | G64: 0 | H64: 0 | I64: 0 | J64: 0 | K64: 0
A65: 36 | B65: Trương Bỉnh Lê Đạt | C65: SV11.3.36 | D65: 0 | E65: 0 | F65: 0 | G65: 0 | H65: 0 | I65: 0 | J65: 0 | K65: 0
A66: 38 | B66: Vũ Thanh Tùng | C66: SV11.3.38 | D66: 0 | E66: 0 | F66: 0 | G66: 0 | H66: 0 | I66: 0 | J66: 0 | K66: 0
A67: 39 | B67: Bùi Việt Hải (NVC) | C67: SV11.3.39 | D67: 0 | E67: 0 | F67: 0 | G67: 0 | H67: 0 | I67: 0 | J67: 0 | K67: 0
A68: 40 | B68: Đào Thị Mai Anh (N.V.Cừ) | C68: SV11.3.40 | D68: 0 | E68: 0 | F68: 0 | G68: 0 | H68: 0 | I68: 0 | J68: 0 | K68: 0
A69: 41 | B69: Đinh Vũ Hà Anh (N.V.Cừ) | C69: SV11.3.41 | D69: 0 | E69: 0 | F69: 0 | G69: 0 | H69: 0 | I69: 0 | J69: 0 | K69: 0
A70: 42 | B70: Hoàng Thu Thuỷ (N.V.Cừ) | C70: SV11.3.42 | D70: 0 | E70: 0 | F70: 0 | G70: 0 | H70: 0 | I70: 0 | J70: 0 | K70: 0
... A80: 52 | B80: Nguyễn Vũ Đức (11A6) | C80: SV11.3.52 | D80: 0 | E80: 0 | F80: 0 | G80: 0 | H80: 0 | I80: 0 | J80: 0 | K80: 0
A81: 1 | B81: Đỗ Vũ Bá Linh | C81: SV11.4.1 | D81: 17/01/2009 | E81: Nam | F81: 0947186969 | G81: Đỗ Mạnh Hoàng | H81: 0947186969 | I81: Vũ Huyền Hạnh | J81: 0945428989 | K81: Tổ 02, Phường Hàng Bông, Quận Hoàn Kiếm, Thành phố Hà Nội
A82: 3 | B82: Lê Đức Thịnh | C82: SV11.4.3 | D82: 13/08/2009 | E82: Nam | F82: 0973306174 | G82: Lê Đức Cường | H82: 0 | I82: Nguyễn Thị Hường | J82: 0 | K82: Tổ 7, Phường Phúc Lợi, Quận Long Biên, Thành phố Hà Nội
A83: 4 | B83: Mai Khánh Huyền | C83: SV11.4.4 | D83: 17/02/2009 | E83: Nữ | F83: 0974995404 | G83: Mai Văn Long | H83: 0984829652 | I83: Nguyễn Thị Linh | J83: 0974995404 | K83: SN3, tổ 14, Phường Thạch Bàn, Quận Long Biên, Thành phố Hà Nội
A84: 6 | B84: Nguyễn Đăng Huy | C84: SV11.4.6 | D84: 11/09/2009 | E84: Nam | F84: 0979456039 | G84: Nguyễn Văn Huỳnh | H84: 0 | I84: Vũ Thị Hoa Xim | J84: 0972643497 | K84: 12A05,H1 CC Hope, Phường Phúc Đồng, Quận Long Biên, Thành phố Hà Nội
A85: 17 | B85: Khuất Tiến Minh | C85: SV11.4.17 | D85: 08/04/2009 | E85: Nam | F85: 0989802021 | G85: Khuất Cao Hùng | H85: 0984887584 | I85: Lương Thị Thanh Hồng | J85: 0989802021 | K85: Phường Long Biên, Quận Long Biên, Thành phố Hà Nội
A86: 18 | B86: Nguyễn Hoàng Anh | C86: SV11.4.18 | D86: 0 | E86: 0 | F86: 0 | G86: 0 | H86: 0 | I86: 0 | J86: 0 | K86: 0
A87: 1 | B87: An Đình Khương | C87: SV11.6.1 | D87: 27/06/2009 | E87: Nam | F87: 0388371810 | G87: An Đình Phú | H87: 0986833986 | I87: Nguyễn Thị Hoa Lý | J87: 0388371810 | K87: Tổ 9, Phường Long Biên, Quận Long Biên, Thành phố Hà Nội
A88: 2 | B88: Đàm Thế Sơn | C88: SV11.6.2 | D88: 04/07/2009 | E88: Nam | F88: 0936914655 | G88: Đàm Thế Anh | H88: 0919135044 | I88: Trương Thị Huyền Trang | J88: 0936914655 | K88: Tổ 19, Phường Sài Đồng, Quận Long Biên, Thành phố Hà Nội
A89: 3 | B89: Đặng Thị Minh Anh | C89: SV11.6.3 | D89: 28/09/2009 | E89: Nữ | F89: 0981717668 | G89: Đặng Văn Thắng | H89: 0981717668 | I89: Nguyễn Thị Thanh Huyền | J89: 0862965186 | K89: Thôn Vàng 1, Xã Cổ Bi, Huyện Gia Lâm, Thành phố Hà Nội
A90: 4 | B90: Đào Hà An | C90: SV11.6.4 | D90: 11/02/2009 | E90: Nữ | F90: 0989583171 | G90: Nguyễn Xuân Hà | H90: 0931118376 | I90: Nguyễn Thu Huyền | J90: 0989583171 | K90: Phường Hoàng Văn Thụ, Quận Hoàng Mai, Thành phố Hà Nội
A91: 5 | B91: Đào Tuệ Linh | C91: SV11.6.5 | D91: 04/06/2009 | E91: Nữ | F91: 0983503418 | G91: Đào Thế Thuận | H91: 0848250784 | I91: Đào Thị Thu Hương | J91: 0983503418 | K91: Số nhà 12, ngõ 147, Tổ 12, Phường Cự Khối, Quận Long Biên, Thành phố Hà Nội
A92: 6 | B92: Dương Bảo Khánh | C92: SV11.6.6 | D92: 12/05/2009 | E92: Nam | F92: 0339126768 | G92: Dương Văn Thăng | H92: 0962434435 | I92: Phan Thị Hồng | J92: 0339126768 | K92: Tổ 11, Phường Thạch Bàn, Quận Long Biên, Thành phố Hà Nội
A93: 7 | B93: Hoàng Khánh Phương | C93: SV11.6.7 | D93: 20/11/2009 | E93: Nữ | F93: 0988080724 | G93: Hoàng Việt Thắng | H93: 0988080724 | I93: Trần Phương Nhung | J93: 0988080724 | K93: Phường Khương Mai, Quận Thanh Xuân, Thành phố Hà Nội
A94: 8 | B94: Lê Minh Sơn | C94: SV11.6.8 | D94: 26/11/2009 | E94: Nam | F94: 0988765298 | G94: Lê Văn Hoàng | H94: 0977207843 | I94: Lê Thị Thanh Nghìn | J94: 0988765298 | K94: Tổ dân phố Kiên Thành, Trâu Quỳ, Gia Lâm, Thành phố Hà Nội
A95: 9 | B95: Lê Việt Cường | C95: SV11.6.9 | D95: 05/11/2009 | E95: Nam | F95: 0987986631 | G95: Lê Văn Hiến | H95: 0988150166 | I95: Nguyễn Thị Thu | J95: 0987986631 | K95: Tổ 25, Phường Ngọc Thuỵ, Quận Long Biên, Thành phố Hà Nội
A96: 10 | B96: Lê Yến Nhi | C96: SV11.6.10 | D96: 15/10/2009 | E96: Nữ | F96: 0984870784 | G96: Lê Văn Tá | H96: 0334424076 | I96: Vũ Thị Lan | J96: 0984870784 | K96: Tổ 10, Phường Cự Khối, Quận Long Biên, Thành phố Hà Nội
A97: 11 | B97: Mai Hải Phong | C97: SV11.6.11 | D97: 05/02/2009 | E97: Nam | F97: 0986564452 | G97: Mai Xuân Đĩnh | H97: 086 7838389 | I97: Nguyễn Thị Loan | J97: 0986564452 | K97: Nhà số 3, Ngõ 88, Tổ 3, Phường Thạch Bàn, Quận Long Biên, Thành phố Hà Nội
A98: 12 | B98: Ngô Gia Bảo Nhi | C98: SV11.6.12 | D98: 20/05/2009 | E98: Nữ | F98: 0949526682 | G98: Ngô Đại Hải | H98: 0949526682 | I98: Trần Thanh Hường | J98: 0902084499 | K98: Tổ 5, Phường Cự Khối, Quận Long Biên, Thành phố Hà Nội
... A117: 33 | B117: Vũ Minh Đức | C117: SV11.6.33 | D117: 16/09/2009 | E117: Nam | F117: 0978171977 | G117: Vũ Văn Hưởng | H117: 0359824087 | I117: Nguyễn Thị Trinh | J117: 0978171977 | K117: Tổ 8, Phường Thượng Thanh, Quận Long Biên, Thành phố Hà Nội
A118: 34 | B118: Lê Nguyễn Hồng Anh | C118: SV11.6.34 | D118: #N/A | E118: #N/A | F118: #N/A | G118: #N/A | H118: #N/A | I118: #N/A | J118: #N/A | K118: #N/A
A119: 35 | B119: Nguyễn Ngọc Thanh (11A7) | C119: SV11.6.35 | D119: #N/A | E119: #N/A | F119: #N/A | G119: #N/A | H119: #N/A | I119: #N/A | J119: #N/A | K119: #N/A
A120: 36 | B120: Đinh Minh Hằng (11A13) | C120: SV11.6.36 | D120: #N/A | E120: #N/A | F120: #N/A | G120: #N/A | H120: #N/A | I120: #N/A | J120: #N/A | K120: #N/A
A121: 37 | B121: Hà Thu Thảo | C121: SV11.6.37 | D121: 24/11/2009 | E121: Nữ | F121: 0976401969 | G121: Hà Tuấn Anh | H121: 0913028795 | I121: Nguyễn Thị Hồng | J121: 0976401969 | K121: Thôn Hạ, Xã Dương Hà, Huyện Gia Lâm, Thành phố Hà Nội
A122: 38 | B122: Bùi Việt Hải (11A2) | C122: SV11.6.38 | D122: #N/A | E122: #N/A | F122: #N/A | G122: #N/A | H122: #N/A | I122: #N/A | J122: #N/A | K122: #N/A
A123: 4 | B123: Đỗ Hiếu Anh | C123: SV11.7.4 | D123: 0 | E123: 0 | F123: 0 | G123: 0 | H123: 0 | I123: 0 | J123: 0 | K123: 0
A124: 11 | B124: Nguyễn Ngọc Mai | C124: SV11.7.11 | D124: 0 | E124: 0 | F124: 0 | G124: 0 | H124: 0 | I124: 0 | J124: 0 | K124: 0
A125: 13 | B125: Phạm Hoàng Minh | C125: SV11.7.13 | D125: 0 | E125: 0 | F125: 0 | G125: 0 | H125: 0 | I125: 0 | J125: 0 | K125: 0
A126: 17 | B126: Vũ Quỳnh Trang | C126: SV11.7.17 | D126: 0 | E126: 0 | F126: 0 | G126: 0 | H126: 0 | I126: 0 | J126: 0 | K126: 0
A127: 1 | B127: Bùi Gia Huy | C127: SV11.8.1 | D127: 27/09/2009 | E127: Nam | F127: 0899405766 | G127: Bùi Văn Hiền | H127: 0944629983 | I127: Lê Thị Bích Ngọc | J127: 0 | K127: số 66 ngõ 1 tổ 25 phường Bồ Đề. Long Biên- Hà Nội
...
